Workbook

Sheet Dashboard
B1: Digital Banking Request Dashboard
B3: As-of date used | C3: =IF(ISNUMBER(C4),C4,TODAY()) -> 46321 | E3: Fictional data for portfolio purposes. All figures calculate from the Request Tracker sheet.
B4: Override date (optional)
B6: Total Requests | C6: Open Requests | D6: Overdue | E6: Due Soon | F6: High Priority Open | G6: SLA Compliance | H6: Avg Turnaround (days) | I6: Completion Rate
B7: =COUNT('Request Tracker'!$B$6:$B$65) -> 40 | C7: =COUNTIFS('Request Tracker'!$B$6:$B$65,">0",'Request Tracker'!$G$6:$G$65,"<>Completed") -> 25 | D7: =COUNTIF('Request Tracker'!$P$6:$P$65,"OVERDUE") -> 4 | E7: =COUNTIF('Request Tracker'!$P$6:$P$65,"Due Soon") -> 7 | F7: =COUNTIFS('Request Tracker'!$F$6:$F$65,"High",'Request Tracker'!$G$6:$G$65,"<>Completed",'Request Tracker'!$B$6:$B$65,">0") -> 10 | G7: =IFERROR(COUNTIF('Request Tracker'!$Q$6:$Q$65,"Met")/(COUNTIF('Request Tracker'!$Q$6:$Q$65,"Met")+COUNTIF('Request Tracker'!$Q$6:$Q$65,"Missed")),0) -> 0.73333333 | H7: =IFERROR(AVERAGE('Request Tracker'!$N$6:$N$65),0) -> 6 | I7: =IF(B7=0,0,COUNTIF('Request Tracker'!$G$6:$G$65,"Completed")/B7) -> 0.375
B9: 1. Requests by Priority and Status
B10: Priority | C10: Pending | D10: In Progress | E10: Completed | F10: Total | G10: Overdue
B11: High | C11: =COUNTIFS('Request Tracker'!$F$6:$F$65,$B11,'Request Tracker'!$G$6:$G$65,C$10) -> 6 | D11: =COUNTIFS('Request Tracker'!$F$6:$F$65,$B11,'Request Tracker'!$G$6:$G$65,D$10) -> 4 | E11: =COUNTIFS('Request Tracker'!$F$6:$F$65,$B11,'Request Tracker'!$G$6:$G$65,E$10) -> 5 | F11: =SUM(C11:E11) -> 15 | G11: =COUNTIFS('Request Tracker'!$F$6:$F$65,$B11,'Request Tracker'!$P$6:$P$65,"OVERDUE") -> 2
B12: Medium | C12: =COUNTIFS('Request Tracker'!$F$6:$F$65,$B12,'Request Tracker'!$G$6:$G$65,C$10) -> 4 | D12: =COUNTIFS('Request Tracker'!$F$6:$F$65,$B12,'Request Tracker'!$G$6:$G$65,D$10) -> 5 | E12: =COUNTIFS('Request Tracker'!$F$6:$F$65,$B12,'Request Tracker'!$G$6:$G$65,E$10) -> 8 | F12: =SUM(C12:E12) -> 17 | G12: =COUNTIFS('Request Tracker'!$F$6:$F$65,$B12,'Request Tracker'!$P$6:$P$65,"OVERDUE") -> 0
B13: Low | C13: =COUNTIFS('Request Tracker'!$F$6:$F$65,$B13,'Request Tracker'!$G$6:$G$65,C$10) -> 3 | D13: =COUNTIFS('Request Tracker'!$F$6:$F$65,$B13,'Request Tracker'!$G$6:$G$65,D$10) -> 3 | E13: =COUNTIFS('Request Tracker'!$F$6:$F$65,$B13,'Request Tracker'!$G$6:$G$65,E$10) -> 2 | F13: =SUM(C13:E13) -> 8 | G13: =COUNTIFS('Request Tracker'!$F$6:$F$65,$B13,'Request Tracker'!$P$6:$P$65,"OVERDUE") -> 2
B14: Total | C14: =SUM(C11:C13) -> 13 | D14: =SUM(D11:D13) -> 12 | E14: =SUM(E11:E13) -> 15 | F14: =SUM(F11:F13) -> 40 | G14: =SUM(G11:G13) -> 4
B16: 2. Performance by Department
B17: Department | C17: Total | D17: Open | E17: Overdue | F17: SLA Met % | G17: Avg Turnaround (days)
B18: =Lists!G5 -> IT | C18: =COUNTIFS('Request Tracker'!$C$6:$C$65,$B18,'Request Tracker'!$B$6:$B$65,">0") -> 7 | D18: =COUNTIFS('Request Tracker'!$C$6:$C$65,$B18,'Request Tracker'!$G$6:$G$65,"<>Completed",'Request Tracker'!$B$6:$B$65,">0") -> 3 | E18: =COUNTIFS('Request Tracker'!$C$6:$C$65,$B18,'Request Tracker'!$P$6:$P$65,"OVERDUE") -> 1 | F18: =IFERROR(COUNTIFS('Request Tracker'!$C$6:$C$65,$B18,'Request Tracker'!$Q$6:$Q$65,"Met")/(COUNTIFS('Request Tracker'!$C$6:$C$65,$B18,'Request Tracker'!$Q$6:$Q$65,"Met")+COUNTIFS('Request Tracker'!$C$6:$C$65,$B18,'Request Tracker'!$Q$6:$Q$65,"Missed")),"-") -> 1 | G18: =IFERROR(AVERAGEIFS('Request Tracker'!$N$6:$N$65,'Request Tracker'!$C$6:$C$65,$B18),"-") -> 5
B19: =Lists!G6 -> Operations | C19: =COUNTIFS('Request Tracker'!$C$6:$C$65,$B19,'Request Tracker'!$B$6:$B$65,">0") -> 6 | D19: =COUNTIFS('Request Tracker'!$C$6:$C$65,$B19,'Request Tracker'!$G$6:$G$65,"<>Completed",'Request Tracker'!$B$6:$B$65,">0") -> 4 | E19: =COUNTIFS('Request Tracker'!$C$6:$C$65,$B19,'Request Tracker'!$P$6:$P$65,"OVERDUE") -> 1 | F19: =IFERROR(COUNTIFS('Request Tracker'!$C$6:$C$65,$B19,'Request Tracker'!$Q$6:$Q$65,"Met")/(COUNTIFS('Request Tracker'!$C$6:$C$65,$B19,'Request Tracker'!$Q$6:$Q$65,"Met")+COUNTIFS('Request Tracker'!$C$6:$C$65,$B19,'Request Tracker'!$Q$6:$Q$65,"Missed")),"-") -> 1 | G19: =IFERROR(AVERAGEIFS('Request Tracker'!$N$6:$N$65,'Request Tracker'!$C$6:$C$65,$B19),"-") -> 3.5
B20: =Lists!G7 -> Digital Banking | C20: =COUNTIFS('Request Tracker'!$C$6:$C$65,$B20,'Request Tracker'!$B$6:$B$65,">0") -> 7 | D20: =COUNTIFS('Request Tracker'!$C$6:$C$65,$B20,'Request Tracker'!$G$6:$G$65,"<>Completed",'Request Tracker'!$B$6:$B$65,">0") -> 4 | E20: =COUNTIFS('Request Tracker'!$C$6:$C$65,$B20,'Request Tracker'!$P$6:$P$65,"OVERDUE") -> 0 | F20: =IFERROR(COUNTIFS('Request Tracker'!$C$6:$C$65,$B20,'Request Tracker'!$Q$6:$Q$65,"Met")/(COUNTIFS('Request Tracker'!$C$6:$C$65,$B20,'Request Tracker'!$Q$6:$Q$65,"Met")+COUNTIFS('Request Tracker'!$C$6:$C$65,$B20,'Request Tracker'!$Q$6:$Q$65,"Missed")),"-") -> 0.66666667 | G20: =IFERROR(AVERAGEIFS('Request Tracker'!$N$6:$N$65,'Request Tracker'!$C$6:$C$65,$B20),"-") -> 4.6666667
B21: =Lists!G8 -> Compliance | C21: =COUNTIFS('Request Tracker'!$C$6:$C$65,$B21,'Request Tracker'!$B$6:$B$65,">0") -> 4 | D21: =COUNTIFS('Request Tracker'!$C$6:$C$65,$B21,'Request Tracker'!$G$6:$G$65,"<>Completed",'Request Tracker'!$B$6:$B$65,">0") -> 2 | E21: =COUNTIFS('Request Tracker'!$C$6:$C$65,$B21,'Request Tracker'!$P$6:$P$65,"OVERDUE") -> 0 | F21: =IFERROR(COUNTIFS('Request Tracker'!$C$6:$C$65,$B21,'Request Tracker'!$Q$6:$Q$65,"Met")/(COUNTIFS('Request Tracker'!$C$6:$C$65,$B21,'Request Tracker'!$Q$6:$Q$65,"Met")+COUNTIFS('Request Tracker'!$C$6:$C$65,$B21,'Request Tracker'!$Q$6:$Q$65,"Missed")),"-") -> 1 | G21: =IFERROR(AVERAGEIFS('Request Tracker'!$N$6:$N$65,'Request Tracker'!$C$6:$C$65,$B21),"-") -> 6.5
B22: =Lists!G9 -> Customer Support | C22: =COUNTIFS('Request Tracker'!$C$6:$C$65,$B22,'Request Tracker'!$B$6:$B$65,">0") -> 5 | D22: =COUNTIFS('Request Tracker'!$C$6:$C$65,$B22,'Request Tracker'!$G$6:$G$65,"<>Completed",'Request Tracker'!$B$6:$B$65,">0") -> 4 | E22: =COUNTIFS('Request Tracker'!$C$6:$C$65,$B22,'Request Tracker'!$P$6:$P$65,"OVERDUE") -> 0 | F22: =IFERROR(COUNTIFS('Request Tracker'!$C$6:$C$65,$B22,'Request Tracker'!$Q$6:$Q$65,"Met")/(COUNTIFS('Request Tracker'!$C$6:$C$65,$B22,'Request Tracker'!$Q$6:$Q$65,"Met")+COUNTIFS('Request Tracker'!$C$6:$C$65,$B22,'Request Tracker'!$Q$6:$Q$65,"Missed")),"-") -> 0 | G22: =IFERROR(AVERAGEIFS('Request Tracker'!$N$6:$N$65,'Request Tracker'!$C$6:$C$65,$B22),"-") -> 3
B23: =Lists!G10 -> Risk | C23: =COUNTIFS('Request Tracker'!$C$6:$C$65,$B23,'Request Tracker'!$B$6:$B$65,">0") -> 4 | D23: =COUNTIFS('Request Tracker'!$C$6:$C$65,$B23,'Request Tracker'!$G$6:$G$65,"<>Completed",'Request Tracker'!$B$6:$B$65,">0") -> 3 | E23: =COUNTIFS('Request Tracker'!$C$6:$C$65,$B23,'Request Tracker'!$P$6:$P$65,"OVERDUE") -> 1 | F23: =IFERROR(COUNTIFS('Request Tracker'!$C$6:$C$65,$B23,'Request Tracker'!$Q$6:$Q$65,"Met")/(COUNTIFS('Request Tracker'!$C$6:$C$65,$B23,'Request Tracker'!$Q$6:$Q$65,"Met")+COUNTIFS('Request Tracker'!$C$6:$C$65,$B23,'Request Tracker'!$Q$6:$Q$65,"Missed")),"-") -> 1 | G23: =IFERROR(AVERAGEIFS('Request Tracker'!$N$6:$N$65,'Request Tracker'!$C$6:$C$65,$B23),"-") -> 7
B24: =Lists!G11 -> Marketing | C24: =COUNTIFS('Request Tracker'!$C$6:$C$65,$B24,'Request Tracker'!$B$6:$B$65,">0") -> 3 | D24: =COUNTIFS('Request Tracker'!$C$6:$C$65,$B24,'Request Tracker'!$G$6:$G$65,"<>Completed",'Request Tracker'!$B$6:$B$65,">0") -> 2 | E24: =COUNTIFS('Request Tracker'!$C$6:$C$65,$B24,'Request Tracker'!$P$6:$P$65,"OVERDUE") -> 1 | F24: =IFERROR(COUNTIFS('Request Tracker'!$C$6:$C$65,$B24,'Request Tracker'!$Q$6:$Q$65,"Met")/(COUNTIFS('Request Tracker'!$C$6:$C$65,$B24,'Request Tracker'!$Q$6:$Q$65,"Met")+COUNTIFS('Request Tracker'!$C$6:$C$65,$B24,'Request Tracker'!$Q$6:$Q$65,"Missed")),"-") -> 0 | G24: =IFERROR(AVERAGEIFS('Request Tracker'!$N$6:$N$65,'Request Tracker'!$C$6:$C$65,$B24),"-") -> 13
B25: =Lists!G12 -> Finance | C25: =COUNTIFS('Request Tracker'!$C$6:$C$65,$B25,'Request Tracker'!$B$6:$B$65,">0") -> 4 | D25: =COUNTIFS('Request Tracker'!$C$6:$C$65,$B25,'Request Tracker'!$G$6:$G$65,"<>Completed",'Request Tracker'!$B$6:$B$65,">0") -> 3 | E25: =COUNTIFS('Request Tracker'!$C$6:$C$65,$B25,'Request Tracker'!$P$6:$P$65,"OVERDUE") -> 0 | F25: =IFERROR(COUNTIFS('Request Tracker'!$C$6:$C$65,$B25,'Request Tracker'!$Q$6:$Q$65,"Met")/(COUNTIFS('Request Tracker'!$C$6:$C$65,$B25,'Request Tracker'!$Q$6:$Q$65,"Met")+COUNTIFS('Request Tracker'!$C$6:$C$65,$B25,'Request Tracker'!$Q$6:$Q$65,"Missed")),"-") -> 0 | G25: =IFERROR(AVERAGEIFS('Request Tracker'!$N$6:$N$65,'Request Tracker'!$C$6:$C$65,$B25),"-") -> 13
B26: Total | C26: =SUM(C18:C25) -> 40 | D26: =SUM(D18:D25) -> 25 | E26: =SUM(E18:E25) -> 4 | F26: =G7 -> 0.73333333 | G26: =H7 -> 6
B28: 3. Assignee Workload vs Capacity
B29: Assignee | C29: Department | D29: Open | E29: Overdue | F29: Capacity | G29: Utilization
B30: =Team!A5 -> Ayesha Khan | C30: =Team!B5 -> Digital Banking | D30: =COUNTIFS('Request Tracker'!$H$6:$H$65,$B30,'Request Tracker'!$G$6:$G$65,"<>Completed",'Request Tracker'!$B$6:$B$65,">0") -> 3 | E30: =COUNTIFS('Request Tracker'!$H$6:$H$65,$B30,'Request Tracker'!$P$6:$P$65,"OVERDUE") -> 0 | F30: =Team!C5 -> 8 | G30: =IF(F30=0,0,D30/F30) -> 0.375
B31: =Team!A6 -> Hamza Malik | C31: =Team!B6 -> IT | D31: =COUNTIFS('Request Tracker'!$H$6:$H$65,$B31,'Request Tracker'!$G$6:$G$65,"<>Completed",'Request Tracker'!$B$6:$B$65,">0") -> 4 | E31: =COUNTIFS('Request Tracker'!$H$6:$H$65,$B31,'Request Tracker'!$P$6:$P$65,"OVERDUE") -> 1 | F31: =Team!C6 -> 8 | G31: =IF(F31=0,0,D31/F31) -> 0.5
B32: =Team!A7 -> Sana Raza | C32: =Team!B7 -> Operations | D32: =COUNTIFS('Request Tracker'!$H$6:$H$65,$B32,'Request Tracker'!$G$6:$G$65,"<>Completed",'Request Tracker'!$B$6:$B$65,">0") -> 4 | E32: =COUNTIFS('Request Tracker'!$H$6:$H$65,$B32,'Request Tracker'!$P$6:$P$65,"OVERDUE") -> 1 | F32: =Team!C7 -> 7 | G32: =IF(F32=0,0,D32/F32) -> 0.57142857
B33: =Team!A8 -> Bilal Ahmed | C33: =Team!B8 -> Compliance | D33: =COUNTIFS('Request Tracker'!$H$6:$H$65,$B33,'Request Tracker'!$G$6:$G$65,"<>Completed",'Request Tracker'!$B$6:$B$65,">0") -> 3 | E33: =COUNTIFS('Request Tracker'!$H$6:$H$65,$B33,'Request Tracker'!$P$6:$P$65,"OVERDUE") -> 0 | F33: =Team!C8 -> 6 | G33: =IF(F33=0,0,D33/F33) -> 0.5
B34: =Team!A9 -> Fatima Noor | C34: =Team!B9 -> Customer Support | D34: =COUNTIFS('Request Tracker'!$H$6:$H$65,$B34,'Request Tracker'!$G$6:$G$65,"<>Completed",'Request Tracker'!$B$6:$B$65,">0") -> 3 | E34: =COUNTIFS('Request Tracker'!$H$6:$H$65,$B34,'Request Tracker'!$P$6:$P$65,"OVERDUE") -> 0 | F34: =Team!C9 -> 7 | G34: =IF(F34=0,0,D34/F34) -> 0.42857143
B35: =Team!A10 -> Usman Tariq | C35: =Team!B10 -> Risk | D35: =COUNTIFS('Request Tracker'!$H$6:$H$65,$B35,'Request Tracker'!$G$6:$G$65,"<>Completed",'Request Tracker'!$B$6:$B$65,">0") -> 2 | E35: =COUNTIFS('Request Tracker'!$H$6:$H$65,$B35,'Request Tracker'!$P$6:$P$65,"OVERDUE") -> 1 | F35: =Team!C10 -> 5 | G35: =IF(F35=0,0,D35/F35) -> 0.4
B36: =Team!A11 -> Zainab Ali | C36: =Team!B11 -> Finance | D36: =COUNTIFS('Request Tracker'!$H$6:$H$65,$B36,'Request Tracker'!$G$6:$G$65,"<>Completed",'Request Tracker'!$B$6:$B$65,">0") -> 2 | E36: =COUNTIFS('Request Tracker'!$H$6:$H$65,$B36,'Request Tracker'!$P$6:$P$65,"OVERDUE") -> 0 | F36: =Team!C11 -> 6 | G36: =IF(F36=0,0,D36/F36) -> 0.33333333
B37: =Team!A12 -> Omar Siddiqui | C37: =Team!B12 -> Digital Banking | D37: =COUNTIFS('Request Tracker'!$H$6:$H$65,$B37,'Request Tracker'!$G$6:$G$65,"<>Completed",'Request Tracker'!$B$6:$B$65,">0") -> 4 | E37: =COUNTIFS('Request Tracker'!$H$6:$H$65,$B37,'Request Tracker'!$P$6:$P$65,"OVERDUE") -> 1 | F37: =Team!C12 -> 8 | G37: =IF(F37=0,0,D37/F37) -> 0.5
B39: 4. Aging of Open Requests
B40: Age Bucket | C40: Open Requests
B41: 0 to 3 days | C41: =COUNTIFS('Request Tracker'!$O$6:$O$65,">=0",'Request Tracker'!$O$6:$O$65,"<=3") -> 9
B42: 4 to 7 days | C42: =COUNTIFS('Request Tracker'!$O$6:$O$65,">=4",'Request Tracker'!$O$6:$O$65,"<=7") -> 12
B43: 8 to 14 days | C43: =COUNTIFS('Request Tracker'!$O$6:$O$65,">=8",'Request Tracker'!$O$6:$O$65,"<=14") -> 3
B44: 15+ days | C44: =COUNTIFS('Request Tracker'!$O$6:$O$65,">=15") -> 1
B45: Total | C45: =SUM(C41:C44) -> 25 | D45: =IF(C45=C7,"Matches open","CHECK") -> Matches open
B47: 5. Top 5 Requests at Risk (open, ranked by risk score)
B48: Request | C48: Department | D48: Assigned To | E48: Deadline | F48: Flag | G48: Risk Score | H48: Row #
B49: =IF($H49="","",INDEX('Request Tracker'!$A$6:$A$65,$H49)&" - "&INDEX('Request Tracker'!$E$6:$E$65,$H49)) -> DB-006 - Password reset flow fix | C49: =IF($H49="","",INDEX('Request Tracker'!$C$6:$C$65,$H49)) -> IT | D49: =IF($H49="","",INDEX('Request Tracker'!$H$6:$H$65,$H49)) -> Hamza Malik | E49: =IF($H49="","",INDEX('Request Tracker'!$I$6:$I$65,$H49)) -> 46319 | F49: =IF($H49="","",INDEX('Request Tracker'!$P$6:$P$65,$H49)) -> OVERDUE | G49: =IF($H49="","",INDEX('Request Tracker'!$R$6:$R$65,$H49)) -> 9 | H49: =IFERROR(IF(LARGE('Request Tracker'!$S$6:$S$65,1)<1,"",MATCH(LARGE('Request Tracker'!$S$6:$S$65,1),'Request Tracker'!$S$6:$S$65,0)),"") -> 6
B50: =IF($H50="","",INDEX('Request Tracker'!$A$6:$A$65,$H50)&" - "&INDEX('Request Tracker'!$E$6:$E$65,$H50)) -> DB-009 - Fraud alert threshold review | C50: =IF($H50="","",INDEX('Request Tracker'!$C$6:$C$65,$H50)) -> Risk | D50: =IF($H50="","",INDEX('Request Tracker'!$H$6:$H$65,$H50)) -> Usman Tariq | E50: =IF($H50="","",INDEX('Request Tracker'!$I$6:$I$65,$H50)) -> 46317 | F50: =IF($H50="","",INDEX('Request Tracker'!$P$6:$P$65,$H50)) -> OVERDUE | G50: =IF($H50="","",INDEX('Request Tracker'!$R$6:$R$65,$H50)) -> 9 | H50: =IFERROR(IF(LARGE('Request Tracker'!$S$6:$S$65,2)<1,"",MATCH(LARGE('Request Tracker'!$S$6:$S$65,2),'Request Tracker'!$S$6:$S$65,0)),"") -> 9
B51: =IF($H51="","",INDEX('Request Tracker'!$A$6:$A$65,$H51)&" - "&INDEX('Request Tracker'!$E$6:$E$65,$H51)) -> DB-004 - KYC process review | C51: =IF($H51="","",INDEX('Request Tracker'!$C$6:$C$65,$H51)) -> Compliance | D51: =IF($H51="","",INDEX('Request Tracker'!$H$6:$H$65,$H51)) -> Bilal Ahmed | E51: =IF($H51="","",INDEX('Request Tracker'!$I$6:$I$65,$H51)) -> 46322 | F51: =IF($H51="","",INDEX('Request Tracker'!$P$6:$P$65,$H51)) -> Due Soon | G51: =IF($H51="","",INDEX('Request Tracker'!$R$6:$R$65,$H51)) -> 6 | H51: =IFERROR(IF(LARGE('Request Tracker'!$S$6:$S$65,3)<1,"",MATCH(LARGE('Request Tracker'!$S$6:$S$65,3),'Request Tracker'!$S$6:$S$65,0)),"") -> 4
B52: =IF($H52="","",INDEX('Request Tracker'!$A$6:$A$65,$H52)&" - "&INDEX('Request Tracker'!$E$6:$E$65,$H52)) -> DB-018 - Biometric login rollout checklist | C52: =IF($H52="","",INDEX('Request Tracker'!$C$6:$C$65,$H52)) -> Digital Banking | D52: =IF($H52="","",INDEX('Request Tracker'!$H$6:$H$65,$H52)) -> Ayesha Khan | E52: =IF($H52="","",INDEX('Request Tracker'!$I$6:$I$65,$H52)) -> 46323 | F52: =IF($H52="","",INDEX('Request Tracker'!$P$6:$P$65,$H52)) -> Due Soon | G52: =IF($H52="","",INDEX('Request Tracker'!$R$6:$R$65,$H52)) -> 6 | H52: =IFERROR(IF(LARGE('Request Tracker'!$S$6:$S$65,4)<1,"",MATCH(LARGE('Request Tracker'!$S$6:$S$65,4),'Request Tracker'!$S$6:$S$65,0)),"") -> 18
B53: =IF($H53="","",INDEX('Request Tracker'!$A$6:$A$65,$H53)&" - "&INDEX('Request Tracker'!$E$6:$E$65,$H53)) -> DB-020 - Digital channel fee reconciliation | C53: =IF($H53="","",INDEX('Request Tracker'!$C$6:$C$65,$H53)) -> Finance | D53: =IF($H53="","",INDEX('Request Tracker'!$H$6:$H$65,$H53)) -> Zainab Ali | E53: =IF($H53="","",INDEX('Request Tracker'!$I$6:$I$65,$H53)) -> 46321 | F53: =IF($H53="","",INDEX('Request Tracker'!$P$6:$P$65,$H53)) -> Due Soon | G53: =IF($H53="","",INDEX('Request Tracker'!$R$6:$R$65,$H53)) -> 6 | H53: =IFERROR(IF(LARGE('Request Tracker'!$S$6:$S$65,5)<1,"",MATCH(LARGE('Request Tracker'!$S$6:$S$65,5),'Request Tracker'!$S$6:$S$65,0)),"") -> 20
B55: 6. Data Quality Checks
B56: Check | C56: Rows Flagged
B57: Missing completion date | C57: =COUNTIF('Request Tracker'!$T$6:$T$65,B57) -> 0
B58: Completion date on open request | C58: =COUNTIF('Request Tracker'!$T$6:$T$65,B58) -> 0
B59: Deadline before raised | C59: =COUNTIF('Request Tracker'!$T$6:$T$65,B59) -> 0
B60: Overall | C60: =IF(SUM(C57:C59)=0,"All clear","Review") -> All clear

Sheet Request Tracker
A1: Digital Banking Team Request Tracker
A2: Fictional data for portfolio purposes.
A3: Edit only the yellow-shaded columns A to J. Columns K to T calculate automatically (column S is a hidden sort helper).
A4: As-of date: | B4: =AsOf -> 46321
A5: Request ID | B5: Date Raised | C5: Department | D5: Request Type | E5: Request | F5: Priority | G5: Status | H5: Assigned To | I5: Deadline | J5: Completed On | K5: SLA (days) | L5: SLA Target | M5: Days Left | N5: Turnaround (days) | O5: Age (days) | P5: Flag | Q5: SLA Status | R5: Risk Score | S5: Sort Key | T5: Data Check
A6: DB-001 | B6: 46318 | C6: IT | D6: Access Request | E6: Access request | F6: High | G6: Pending | H6: Hamza Malik | I6: 46325 | K6: =IF($B6="","",IFERROR(INDEX(Lists!$B$5:$B$7,MATCH($F6,Lists!$A$5:$A$7,0)),"")) -> 2 | L6: =IF(OR($B6="",$K6=""),"",WORKDAY($B6,$K6)) -> 46322 | M6: =IF(OR($B6="",$I6=""),"",IF($G6="Completed","",$I6-AsOf)) -> 4 | N6: =IF(OR($B6="",$J6=""),"",$J6-$B6) | O6: =IF($B6="","",IF($G6="Completed","",AsOf-$B6)) -> 3 | P6: =IF($B6="","",IF($G6="Completed",IF(AND($J6<>"",$J6>$I6),"Done (Late)","Done"),IF($I6="","No deadline",IF($I6<AsOf,"OVERDUE",IF($I6-AsOf<=Lists!$B$9,"Due Soon","On Track"))))) -> On Track | Q6: =IF(OR($B6="",$L6=""),"",IF($G6="Completed",IF($J6="","",IF($J6<=$L6,"Met","Missed")),IF(AsOf>$L6,"Breached","Within SLA"))) -> Within SLA | R6: =IF($B6="","",IF($G6="Completed",0,IFERROR(INDEX(Lists!$C$5:$C$7,MATCH($F6,Lists!$A$5:$A$7,0)),1)*IF($I6="",1,IF($I6<AsOf,3,IF($I6-AsOf<=Lists!$B$9,2,1))))) -> 3 | S6: =IF($B6="","",$R6+(1000-ROW())/100000) -> 3.00994 | T6: =IF($B6="","",IF(AND($G6="Completed",$J6=""),"Missing completion date",IF(AND($G6<>"Completed",$J6<>""),"Completion date on open request",IF(AND($I6<>"",$I6<$B6),"Deadline before raised","OK")))) -> OK
A7: DB-002 | B7: 46316 | C7: Operations | D7: Report | E7: Report preparation | F7: Medium | G7: In Progress | H7: Sana Raza | I7: 46326 | K7: =IF($B7="","",IFERROR(INDEX(Lists!$B$5:$B$7,MATCH($F7,Lists!$A$5:$A$7,0)),"")) -> 5 | L7: =IF(OR($B7="",$K7=""),"",WORKDAY($B7,$K7)) -> 46323 | M7: =IF(OR($B7="",$I7=""),"",IF($G7="Completed","",$I7-AsOf)) -> 5 | N7: =IF(OR($B7="",$J7=""),"",$J7-$B7) | O7: =IF($B7="","",IF($G7="Completed","",AsOf-$B7)) -> 5 | P7: =IF($B7="","",IF($G7="Completed",IF(AND($J7<>"",$J7>$I7),"Done (Late)","Done"),IF($I7="","No deadline",IF($I7<AsOf,"OVERDUE",IF($I7-AsOf<=Lists!$B$9,"Due Soon","On Track"))))) -> On Track | Q7: =IF(OR($B7="",$L7=""),"",IF($G7="Completed",IF($J7="","",IF($J7<=$L7,"Met","Missed")),IF(AsOf>$L7,"Breached","Within SLA"))) -> Within SLA | R7: =IF($B7="","",IF($G7="Completed",0,IFERROR(INDEX(Lists!$C$5:$C$7,MATCH($F7,Lists!$A$5:$A$7,0)),1)*IF($I7="",1,IF($I7<AsOf,3,IF($I7-AsOf<=Lists!$B$9,2,1))))) -> 2 | S7: =IF($B7="","",$R7+(1000-ROW())/100000) -> 2.00993 | T7: =IF($B7="","",IF(AND($G7="Completed",$J7=""),"Missing completion date",IF(AND($G7<>"Completed",$J7<>""),"Completion date on open request",IF(AND($I7<>"",$I7<$B7),"Deadline before raised","OK")))) -> OK
A8: DB-003 | B8: 46317 | C8: Digital Banking | D8: Testing Support | E8: Testing support | F8: High | G8: Completed | H8: Ayesha Khan | I8: 46323 | J8: 46318 | K8: =IF($B8="","",IFERROR(INDEX(Lists!$B$5:$B$7,MATCH($F8,Lists!$A$5:$A$7,0)),"")) -> 2 | L8: =IF(OR($B8="",$K8=""),"",WORKDAY($B8,$K8)) -> 46321 | M8: =IF(OR($B8="",$I8=""),"",IF($G8="Completed","",$I8-AsOf)) | N8: =IF(OR($B8="",$J8=""),"",$J8-$B8) -> 1 | O8: =IF($B8="","",IF($G8="Completed","",AsOf-$B8)) | P8: =IF($B8="","",IF($G8="Completed",IF(AND($J8<>"",$J8>$I8),"Done (Late)","Done"),IF($I8="","No deadline",IF($I8<AsOf,"OVERDUE",IF($I8-AsOf<=Lists!$B$9,"Due Soon","On Track"))))) -> Done | Q8: =IF(OR($B8="",$L8=""),"",IF($G8="Completed",IF($J8="","",IF($J8<=$L8,"Met","Missed")),IF(AsOf>$L8,"Breached","Within SLA"))) -> Met | R8: =IF($B8="","",IF($G8="Completed",0,IFERROR(INDEX(Lists!$C$5:$C$7,MATCH($F8,Lists!$A$5:$A$7,0)),1)*IF($I8="",1,IF($I8<AsOf,3,IF($I8-AsOf<=Lists!$B$9,2,1))))) -> 0 | S8: =IF($B8="","",$R8+(1000-ROW())/100000) -> 0.00992 | T8: =IF($B8="","",IF(AND($G8="Completed",$J8=""),"Missing completion date",IF(AND($G8<>"Completed",$J8<>""),"Completion date on open request",IF(AND($I8<>"",$I8<$B8),"Deadline before raised","OK")))) -> OK
A9: DB-004 | B9: 46317 | C9: Compliance | D9: Compliance Review | E9: KYC process review | F9: High | G9: In Progress | H9: Bilal Ahmed | I9: 46322 | K9: =IF($B9="","",IFERROR(INDEX(Lists!$B$5:$B$7,MATCH($F9,Lists!$A$5:$A$7,0)),"")) -> 2 | L9: =IF(OR($B9="",$K9=""),"",WORKDAY($B9,$K9)) -> 46321 | M9: =IF(OR($B9="",$I9=""),"",IF($G9="Completed","",$I9-AsOf)) -> 1 | N9: =IF(OR($B9="",$J9=""),"",$J9-$B9) | O9: =IF($B9="","",IF($G9="Completed","",AsOf-$B9)) -> 4 | P9: =IF($B9="","",IF($G9="Completed",IF(AND($J9<>"",$J9>$I9),"Done (Late)","Done"),IF($I9="","No deadline",IF($I9<AsOf,"OVERDUE",IF($I9-AsOf<=Lists!$B$9,"Due Soon","On Track"))))) -> Due Soon | Q9: =IF(OR($B9="",$L9=""),"",IF($G9="Completed",IF($J9="","",IF($J9<=$L9,"Met","Missed")),IF(AsOf>$L9,"Breached","Within SLA"))) -> Within SLA | R9: =IF($B9="","",IF($G9="Completed",0,IFERROR(INDEX(Lists!$C$5:$C$7,MATCH($F9,Lists!$A$5:$A$7,0)),1)*IF($I9="",1,IF($I9<AsOf,3,IF($I9-AsOf<=Lists!$B$9,2,1))))) -> 6 | S9: =IF($B9="","",$R9+(1000-ROW())/100000) -> 6.00991 | T9: =IF($B9="","",IF(AND($G9="Completed",$J9=""),"Missing completion date",IF(AND($G9<>"Completed",$J9<>""),"Completion date on open request",IF(AND($I9<>"",$I9<$B9),"Deadline before raised","OK")))) -> OK
A10: DB-005 | B10: 46321 | C10: Customer Support | D10: Documentation | E10: Mobile app FAQ update | F10: Low | G10: Pending | H10: Fatima Noor | I10: 46330 | K10: =IF($B10="","",IFERROR(INDEX(Lists!$B$5:$B$7,MATCH($F10,Lists!$A$5:$A$7,0)),"")) -> 8 | L10: =IF(OR($B10="",$K10=""),"",WORKDAY($B10,$K10)) -> 46331 | M10: =IF(OR($B10="",$I10=""),"",IF($G10="Completed","",$I10-AsOf)) -> 9 | N10: =IF(OR($B10="",$J10=""),"",$J10-$B10) | O10: =IF($B10="","",IF($G10="Completed","",AsOf-$B10)) -> 0 | P10: =IF($B10="","",IF($G10="Completed",IF(AND($J10<>"",$J10>$I10),"Done (Late)","Done"),IF($I10="","No deadline",IF($I10<AsOf,"OVERDUE",IF($I10-AsOf<=Lists!$B$9,"Due Soon","On Track"))))) -> On Track | Q10: =IF(OR($B10="",$L10=""),"",IF($G10="Completed",IF($J10="","",IF($J10<=$L10,"Met","Missed")),IF(AsOf>$L10,"Breached","Within SLA"))) -> Within SLA | R10: =IF($B10="","",IF($G10="Completed",0,IFERROR(INDEX(Lists!$C$5:$C$7,MATCH($F10,Lists!$A$5:$A$7,0)),1)*IF($I10="",1,IF($I10<AsOf,3,IF($I10-AsOf<=Lists!$B$9,2,1))))) -> 1 | S10: =IF($B10="","",$R10+(1000-ROW())/100000) -> 1.0099 | T10: =IF($B10="","",IF(AND($G10="Completed",$J10=""),"Missing completion date",IF(AND($G10<>"Completed",$J10<>""),"Completion date on open request",IF(AND($I10<>"",$I10<$B10),"Deadline before raised","OK")))) -> OK
A11: DB-006 | B11: 46314 | C11: IT | D11: Incident Fix | E11: Password reset flow fix | F11: High | G11: Pending | H11: Hamza Malik | I11: 46319 | K11: =IF($B11="","",IFERROR(INDEX(Lists!$B$5:$B$7,MATCH($F11,Lists!$A$5:$A$7,0)),"")) -> 2 | L11: =IF(OR($B11="",$K11=""),"",WORKDAY($B11,$K11)) -> 46316 | M11: =IF(OR($B11="",$I11=""),"",IF($G11="Completed","",$I11-AsOf)) -> -2 | N11: =IF(OR($B11="",$J11=""),"",$J11-$B11) | O11: =IF($B11="","",IF($G11="Completed","",AsOf-$B11)) -> 7 | P11: =IF($B11="","",IF($G11="Completed",IF(AND($J11<>"",$J11>$I11),"Done (Late)","Done"),IF($I11="","No deadline",IF($I11<AsOf,"OVERDUE",IF($I11-AsOf<=Lists!$B$9,"Due Soon","On Track"))))) -> OVERDUE | Q11: =IF(OR($B11="",$L11=""),"",IF($G11="Completed",IF($J11="","",IF($J11<=$L11,"Met","Missed")),IF(AsOf>$L11,"Breached","Within SLA"))) -> Breached | R11: =IF($B11="","",IF($G11="Completed",0,IFERROR(INDEX(Lists!$C$5:$C$7,MATCH($F11,Lists!$A$5:$A$7,0)),1)*IF($I11="",1,IF($I11<AsOf,3,IF($I11-AsOf<=Lists!$B$9,2,1))))) -> 9 | S11: =IF($B11="","",$R11+(1000-ROW())/100000) -> 9.00989 | T11: =IF($B11="","",IF(AND($G11="Completed",$J11=""),"Missing completion date",IF(AND($G11<>"Completed",$J11<>""),"Completion date on open request",IF(AND($I11<>"",$I11<$B11),"Deadline before raised","OK")))) -> OK
A12: DB-007 | B12: 46311 | C12: Operations | D12: Report | E12: Daily transaction summary | F12: Medium | G12: Completed | H12: Sana Raza | I12: 46318 | J12: 46317 | K12: =IF($B12="","",IFERROR(INDEX(Lists!$B$5:$B$7,MATCH($F12,Lists!$A$5:$A$7,0)),"")) -> 5 | L12: =IF(OR($B12="",$K12=""),"",WORKDAY($B12,$K12)) -> 46318 | M12: =IF(OR($B12="",$I12=""),"",IF($G12="Completed","",$I12-AsOf)) | N12: =IF(OR($B12="",$J12=""),"",$J12-$B12) -> 6 | O12: =IF($B12="","",IF($G12="Completed","",AsOf-$B12)) | P12: =IF($B12="","",IF($G12="Completed",IF(AND($J12<>"",$J12>$I12),"Done (Late)","Done"),IF($I12="","No deadline",IF($I12<AsOf,"OVERDUE",IF($I12-AsOf<=Lists!$B$9,"Due Soon","On Track"))))) -> Done | Q12: =IF(OR($B12="",$L12=""),"",IF($G12="Completed",IF($J12="","",IF($J12<=$L12,"Met","Missed")),IF(AsOf>$L12,"Breached","Within SLA"))) -> Met | R12: =IF($B12="","",IF($G12="Completed",0,IFERROR(INDEX(Lists!$C$5:$C$7,MATCH($F12,Lists!$A$5:$A$7,0)),1)*IF($I12="",1,IF($I12<AsOf,3,IF($I12-AsOf<=Lists!$B$9,2,1))))) -> 0 | S12: =IF($B12="","",$R12+(1000-ROW())/100000) -> 0.00988 | T12: =IF($B12="","",IF(AND($G12="Completed",$J12=""),"Missing completion date",IF(AND($G12<>"Completed",$J12<>""),"Completion date on open request",IF(AND($I12<>"",$I12<$B12),"Deadline before raised","OK")))) -> OK
A13: DB-008 | B13: 46315 | C13: Digital Banking | D13: Testing Support | E13: UAT test case documentation | F13: Medium | G13: In Progress | H13: Omar Siddiqui | I13: 46324 | K13: =IF($B13="","",IFERROR(INDEX(Lists!$B$5:$B$7,MATCH($F13,Lists!$A$5:$A$7,0)),"")) -> 5 | L13: =IF(OR($B13="",$K13=""),"",WORKDAY($B13,$K13)) -> 46322 | M13: =IF(OR($B13="",$I13=""),"",IF($G13="Completed","",$I13-AsOf)) -> 3 | N13: =IF(OR($B13="",$J13=""),"",$J13-$B13) | O13: =IF($B13="","",IF($G13="Completed","",AsOf-$B13)) -> 6 | P13: =IF($B13="","",IF($G13="Completed",IF(AND($J13<>"",$J13>$I13),"Done (Late)","Done"),IF($I13="","No deadline",IF($I13<AsOf,"OVERDUE",IF($I13-AsOf<=Lists!$B$9,"Due Soon","On Track"))))) -> On Track | Q13: =IF(OR($B13="",$L13=""),"",IF($G13="Completed",IF($J13="","",IF($J13<=$L13,"Met","Missed")),IF(AsOf>$L13,"Breached","Within SLA"))) -> Within SLA | R13: =IF($B13="","",IF($G13="Completed",0,IFERROR(INDEX(Lists!$C$5:$C$7,MATCH($F13,Lists!$A$5:$A$7,0)),1)*IF($I13="",1,IF($I13<AsOf,3,IF($I13-AsOf<=Lists!$B$9,2,1))))) -> 2 | S13: =IF($B13="","",$R13+(1000-ROW())/100000) -> 2.00987 | T13: =IF($B13="","",IF(AND($G13="Completed",$J13=""),"Missing completion date",IF(AND($G13<>"Completed",$J13<>""),"Completion date on open request",IF(AND($I13<>"",$I13<$B13),"Deadline before raised","OK")))) -> OK
A14: DB-009 | B14: 46310 | C14: Risk | D14: Compliance Review | E14: Fraud alert threshold review | F14: High | G14: Pending | H14: Usman Tariq | I14: 46317 | K14: =IF($B14="","",IFERROR(INDEX(Lists!$B$5:$B$7,MATCH($F14,Lists!$A$5:$A$7,0)),"")) -> 2 | L14: =IF(OR($B14="",$K14=""),"",WORKDAY($B14,$K14)) -> 46314 | M14: =IF(OR($B14="",$I14=""),"",IF($G14="Completed","",$I14-AsOf)) -> -4 | N14: =IF(OR($B14="",$J14=""),"",$J14-$B14) | O14: =IF($B14="","",IF($G14="Completed","",AsOf-$B14)) -> 11 | P14: =IF($B14="","",IF($G14="Completed",IF(AND($J14<>"",$J14>$I14),"Done (Late)","Done"),IF($I14="","No deadline",IF($I14<AsOf,"OVERDUE",IF($I14-AsOf<=Lists!$B$9,"Due Soon","On Track"))))) -> OVERDUE | Q14: =IF(OR($B14="",$L14=""),"",IF($G14="Completed",IF($J14="","",IF($J14<=$L14,"Met","Missed")),IF(AsOf>$L14,"Breached","Within SLA"))) -> Breached | R14: =IF($B14="","",IF($G14="Completed",0,IFERROR(INDEX(Lists!$C$5:$C$7,MATCH($F14,Lists!$A$5:$A$7,0)),1)*IF($I14="",1,IF($I14<AsOf,3,IF($I14-AsOf<=Lists!$B$9,2,1))))) -> 9 | S14: =IF($B14="","",$R14+(1000-ROW())/100000) -> 9.00986 | T14: =IF($B14="","",IF(AND($G14="Completed",$J14=""),"Missing completion date",IF(AND($G14<>"Completed",$J14<>""),"Completion date on open request",IF(AND($I14<>"",$I14<$B14),"Deadline before raised","OK")))) -> OK
A15: DB-010 | B15: 46314 | C15: Marketing | D15: Documentation | E15: Mobile banking launch banner copy | F15: Low | G15: In Progress | H15: Fatima Noor | I15: 46332 | K15: =IF($B15="","",IFERROR(INDEX(Lists!$B$5:$B$7,MATCH($F15,Lists!$A$5:$A$7,0)),"")) -> 8 | L15: =IF(OR($B15="",$K15=""),"",WORKDAY($B15,$K15)) -> 46324 | M15: =IF(OR($B15="",$I15=""),"",IF($G15="Completed","",$I15-AsOf)) -> 11 | N15: =IF(OR($B15="",$J15=""),"",$J15-$B15) | O15: =IF($B15="","",IF($G15="Completed","",AsOf-$B15)) -> 7 | P15: =IF($B15="","",IF($G15="Completed",IF(AND($J15<>"",$J15>$I15),"Done (Late)","Done"),IF($I15="","No deadline",IF($I15<AsOf,"OVERDUE",IF($I15-AsOf<=Lists!$B$9,"Due Soon","On Track"))))) -> On Track | Q15: =IF(OR($B15="",$L15=""),"",IF($G15="Completed",IF($J15="","",IF($J15<=$L15,"Met","Missed")),IF(AsOf>$L15,"Breached","Within SLA"))) -> Within SLA | R15: =IF($B15="","",IF($G15="Completed",0,IFERROR(INDEX(Lists!$C$5:$C$7,MATCH($F15,Lists!$A$5:$A$7,0)),1)*IF($I15="",1,IF($I15<AsOf,3,IF($I15-AsOf<=Lists!$B$9,2,1))))) -> 1 | S15: =IF($B15="","",$R15+(1000-ROW())/100000) -> 1.00985 | T15: =IF($B15="","",IF(AND($G15="Completed",$J15=""),"Missing completion date",IF(AND($G15<>"Completed",$J15<>""),"Completion date on open request",IF(AND($I15<>"",$I15<$B15),"Deadline before raised","OK")))) -> OK
A16: DB-011 | B16: 46318 | C16: Finance | D16: Report | E16: Monthly fee income report | F16: Medium | G16: Pending | H16: Zainab Ali | I16: 46328 | K16: =IF($B16="","",IFERROR(INDEX(Lists!$B$5:$B$7,MATCH($F16,Lists!$A$5:$A$7,0)),"")) -> 5 | L16: =IF(OR($B16="",$K16=""),"",WORKDAY($B16,$K16)) -> 46325 | M16: =IF(OR($B16="",$I16=""),"",IF($G16="Completed","",$I16-AsOf)) -> 7 | N16: =IF(OR($B16="",$J16=""),"",$J16-$B16) | O16: =IF($B16="","",IF($G16="Completed","",AsOf-$B16)) -> 3 | P16: =IF($B16="","",IF($G16="Completed",IF(AND($J16<>"",$J16>$I16),"Done (Late)","Done"),IF($I16="","No deadline",IF($I16<AsOf,"OVERDUE",IF($I16-AsOf<=Lists!$B$9,"Due Soon","On Track"))))) -> On Track | Q16: =IF(OR($B16="",$L16=""),"",IF($G16="Completed",IF($J16="","",IF($J16<=$L16,"Met","Missed")),IF(AsOf>$L16,"Breached","Within SLA"))) -> Within SLA | R16: =IF($B16="","",IF($G16="Completed",0,IFERROR(INDEX(Lists!$C$5:$C$7,MATCH($F16,Lists!$A$5:$A$7,0)),1)*IF($I16="",1,IF($I16<AsOf,3,IF($I16-AsOf<=Lists!$B$9,2,1))))) -> 2 | S16: =IF($B16="","",$R16+(1000-ROW())/100000) -> 2.00984 | T16: =IF($B16="","",IF(AND($G16="Completed",$J16=""),"Missing completion date",IF(AND($G16<>"Completed",$J16<>""),"Completion date on open request",IF(AND($I16<>"",$I16<$B16),"Deadline before raised","OK")))) -> OK
A17: DB-012 | B17: 46314 | C17: IT | D17: Access Request | E17: API access for payments team | F17: Medium | G17: Completed | H17: Hamza Malik | I17: 46321 | J17: 46321 | K17: =IF($B17="","",IFERROR(INDEX(Lists!$B$5:$B$7,MATCH($F17,Lists!$A$5:$A$7,0)),"")) -> 5 | L17: =IF(OR($B17="",$K17=""),"",WORKDAY($B17,$K17)) -> 46321 | M17: =IF(OR($B17="",$I17=""),"",IF($G17="Completed","",$I17-AsOf)) | N17: =IF(OR($B17="",$J17=""),"",$J17-$B17) -> 7 | O17: =IF($B17="","",IF($G17="Completed","",AsOf-$B17)) | P17: =IF($B17="","",IF($G17="Completed",IF(AND($J17<>"",$J17>$I17),"Done (Late)","Done"),IF($I17="","No deadline",IF($I17<AsOf,"OVERDUE",IF($I17-AsOf<=Lists!$B$9,"Due Soon","On Track"))))) -> Done | Q17: =IF(OR($B17="",$L17=""),"",IF($G17="Completed",IF($J17="","",IF($J17<=$L17,"Met","Missed")),IF(AsOf>$L17,"Breached","Within SLA"))) -> Met | R17: =IF($B17="","",IF($G17="Completed",0,IFERROR(INDEX(Lists!$C$5:$C$7,MATCH($F17,Lists!$A$5:$A$7,0)),1)*IF($I17="",1,IF($I17<AsOf,3,IF($I17-AsOf<=Lists!$B$9,2,1))))) -> 0 | S17: =IF($B17="","",$R17+(1000-ROW())/100000) -> 0.00983 | T17: =IF($B17="","",IF(AND($G17="Completed",$J17=""),"Missing completion date",IF(AND($G17<>"Completed",$J17<>""),"Completion date on open request",IF(AND($I17<>"",$I17<$B17),"Deadline before raised","OK")))) -> OK
A18: DB-013 | B18: 46321 | C18: Customer Support | D18: Report | E18: Complaint log analysis | F18: Low | G18: Pending | H18: Fatima Noor | I18: 46335 | K18: =IF($B18="","",IFERROR(INDEX(Lists!$B$5:$B$7,MATCH($F18,Lists!$A$5:$A$7,0)),"")) -> 8 | L18: =IF(OR($B18="",$K18=""),"",WORKDAY($B18,$K18)) -> 46331 | M18: =IF(OR($B18="",$I18=""),"",IF($G18="Completed","",$I18-AsOf)) -> 14 | N18: =IF(OR($B18="",$J18=""),"",$J18-$B18) | O18: =IF($B18="","",IF($G18="Completed","",AsOf-$B18)) -> 0 | P18: =IF($B18="","",IF($G18="Completed",IF(AND($J18<>"",$J18>$I18),"Done (Late)","Done"),IF($I18="","No deadline",IF($I18<AsOf,"OVERDUE",IF($I18-AsOf<=Lists!$B$9,"Due Soon","On Track"))))) -> On Track | Q18: =IF(OR($B18="",$L18=""),"",IF($G18="Completed",IF($J18="","",IF($J18<=$L18,"Met","Missed")),IF(AsOf>$L18,"Breached","Within SLA"))) -> Within SLA | R18: =IF($B18="","",IF($G18="Completed",0,IFERROR(INDEX(Lists!$C$5:$C$7,MATCH($F18,Lists!$A$5:$A$7,0)),1)*IF($I18="",1,IF($I18<AsOf,3,IF($I18-AsOf<=Lists!$B$9,2,1))))) -> 1 | S18: =IF($B18="","",$R18+(1000-ROW())/100000) -> 1.00982 | T18: =IF($B18="","",IF(AND($G18="Completed",$J18=""),"Missing completion date",IF(AND($G18<>"Completed",$J18<>""),"Completion date on open request",IF(AND($I18<>"",$I18<$B18),"Deadline before raised","OK")))) -> OK
A19: DB-014 | B19: 46307 | C19: Digital Banking | D19: Documentation | E19: Internet banking user guide | F19: Medium | G19: Completed | H19: Ayesha Khan | I19: 46316 | J19: 46318 | K19: =IF($B19="","",IFERROR(INDEX(Lists!$B$5:$B$7,MATCH($F19,Lists!$A$5:$A$7,0)),"")) -> 5 | L19: =IF(OR($B19="",$K19=""),"",WORKDAY($B19,$K19)) -> 46314 | M19: =IF(OR($B19="",$I19=""),"",IF($G19="Completed","",$I19-AsOf)) | N19: =IF(OR($B19="",$J19=""),"",$J19-$B19) -> 11 | O19: =IF($B19="","",IF($G19="Completed","",AsOf-$B19)) | P19: =IF($B19="","",IF($G19="Completed",IF(AND($J19<>"",$J19>$I19),"Done (Late)","Done"),IF($I19="","No deadline",IF($I19<AsOf,"OVERDUE",IF($I19-AsOf<=Lists!$B$9,"Due Soon","On Track"))))) -> Done (Late) | Q19: =IF(OR($B19="",$L19=""),"",IF($G19="Completed",IF($J19="","",IF($J19<=$L19,"Met","Missed")),IF(AsOf>$L19,"Breached","Within SLA"))) -> Missed | R19: =IF($B19="","",IF($G19="Completed",0,IFERROR(INDEX(Lists!$C$5:$C$7,MATCH($F19,Lists!$A$5:$A$7,0)),1)*IF($I19="",1,IF($I19<AsOf,3,IF($I19-AsOf<=Lists!$B$9,2,1))))) -> 0 | S19: =IF($B19="","",$R19+(1000-ROW())/100000) -> 0.00981 | T19: =IF($B19="","",IF(AND($G19="Completed",$J19=""),"Missing completion date",IF(AND($G19<>"Completed",$J19<>""),"Completion date on open request",IF(AND($I19<>"",$I19<$B19),"Deadline before raised","OK")))) -> OK
A20: DB-015 | B20: 46317 | C20: Compliance | D20: Compliance Review | E20: Audit evidence collection | F20: High | G20: In Progress | H20: Bilal Ahmed | I20: 46329 | K20: =IF($B20="","",IFERROR(INDEX(Lists!$B$5:$B$7,MATCH($F20,Lists!$A$5:$A$7,0)),"")) -> 2 | L20: =IF(OR($B20="",$K20=""),"",WORKDAY($B20,$K20)) -> 46321 | M20: =IF(OR($B20="",$I20=""),"",IF($G20="Completed","",$I20-AsOf)) -> 8 | N20: =IF(OR($B20="",$J20=""),"",$J20-$B20) | O20: =IF($B20="","",IF($G20="Completed","",AsOf-$B20)) -> 4 | P20: =IF($B20="","",IF($G20="Completed",IF(AND($J20<>"",$J20>$I20),"Done (Late)","Done"),IF($I20="","No deadline",IF($I20<AsOf,"OVERDUE",IF($I20-AsOf<=Lists!$B$9,"Due Soon","On Track"))))) -> On Track | Q20: =IF(OR($B20="",$L20=""),"",IF($G20="Completed",IF($J20="","",IF($J20<=$L20,"Met","Missed")),IF(AsOf>$L20,"Breached","Within SLA"))) -> Within SLA | R20: =IF($B20="","",IF($G20="Completed",0,IFERROR(INDEX(Lists!$C$5:$C$7,MATCH($F20,Lists!$A$5:$A$7,0)),1)*IF($I20="",1,IF($I20<AsOf,3,IF($I20-AsOf<=Lists!$B$9,2,1))))) -> 3 | S20: =IF($B20="","",$R20+(1000-ROW())/100000) -> 3.0098 | T20: =IF($B20="","",IF(AND($G20="Completed",$J20=""),"Missing completion date",IF(AND($G20<>"Completed",$J20<>""),"Completion date on open request",IF(AND($I20<>"",$I20<$B20),"Deadline before raised","OK")))) -> OK
A21: DB-016 | B21: 46315 | C21: IT | D21: Change Request | E21: Add OTP timeout parameter | F21: Medium | G21: In Progress | H21: Hamza Malik | I21: 46325 | K21: =IF($B21="","",IFERROR(INDEX(Lists!$B$5:$B$7,MATCH($F21,Lists!$A$5:$A$7,0)),"")) -> 5 | L21: =IF(OR($B21="",$K21=""),"",WORKDAY($B21,$K21)) -> 46322 | M21: =IF(OR($B21="",$I21=""),"",IF($G21="Completed","",$I21-AsOf)) -> 4 | N21: =IF(OR($B21="",$J21=""),"",$J21-$B21) | O21: =IF($B21="","",IF($G21="Completed","",AsOf-$B21)) -> 6 | P21: =IF($B21="","",IF($G21="Completed",IF(AND($J21<>"",$J21>$I21),"Done (Late)","Done"),IF($I21="","No deadline",IF($I21<AsOf,"OVERDUE",IF($I21-AsOf<=Lists!$B$9,"Due Soon","On Track"))))) -> On Track | Q21: =IF(OR($B21="",$L21=""),"",IF($G21="Completed",IF($J21="","",IF($J21<=$L21,"Met","Missed")),IF(AsOf>$L21,"Breached","Within SLA"))) -> Within SLA | R21: =IF($B21="","",IF($G21="Completed",0,IFERROR(INDEX(Lists!$C$5:$C$7,MATCH($F21,Lists!$A$5:$A$7,0)),1)*IF($I21="",1,IF($I21<AsOf,3,IF($I21-AsOf<=Lists!$B$9,2,1))))) -> 2 | S21: =IF($B21="","",$R21+(1000-ROW())/100000) -> 2.00979 | T21: =IF($B21="","",IF(AND($G21="Completed",$J21=""),"Missing completion date",IF(AND($G21<>"Completed",$J21<>""),"Completion date on open request",IF(AND($I21<>"",$I21<$B21),"Deadline before raised","OK")))) -> OK
A22: DB-017 | B22: 46309 | C22: Operations | D22: Incident Fix | E22: Failed fund transfer reconciliation | F22: High | G22: Completed | H22: Sana Raza | I22: 46311 | J22: 46310 | K22: =IF($B22="","",IFERROR(INDEX(Lists!$B$5:$B$7,MATCH($F22,Lists!$A$5:$A$7,0)),"")) -> 2 | L22: =IF(OR($B22="",$K22=""),"",WORKDAY($B22,$K22)) -> 46311 | M22: =IF(OR($B22="",$I22=""),"",IF($G22="Completed","",$I22-AsOf)) | N22: =IF(OR($B22="",$J22=""),"",$J22-$B22) -> 1 | O22: =IF($B22="","",IF($G22="Completed","",AsOf-$B22)) | P22: =IF($B22="","",IF($G22="Completed",IF(AND($J22<>"",$J22>$I22),"Done (Late)","Done"),IF($I22="","No deadline",IF($I22<AsOf,"OVERDUE",IF($I22-AsOf<=Lists!$B$9,"Due Soon","On Track"))))) -> Done | Q22: =IF(OR($B22="",$L22=""),"",IF($G22="Completed",IF($J22="","",IF($J22<=$L22,"Met","Missed")),IF(AsOf>$L22,"Breached","Within SLA"))) -> Met | R22: =IF($B22="","",IF($G22="Completed",0,IFERROR(INDEX(Lists!$C$5:$C$7,MATCH($F22,Lists!$A$5:$A$7,0)),1)*IF($I22="",1,IF($I22<AsOf,3,IF($I22-AsOf<=Lists!$B$9,2,1))))) -> 0 | S22: =IF($B22="","",$R22+(1000-ROW())/100000) -> 0.00978 | T22: =IF($B22="","",IF(AND($G22="Completed",$J22=""),"Missing completion date",IF(AND($G22<>"Completed",$J22<>""),"Completion date on open request",IF(AND($I22<>"",$I22<$B22),"Deadline before raised","OK")))) -> OK
A23: DB-018 | B23: 46316 | C23: Digital Banking | D23: Change Request | E23: Biometric login rollout checklist | F23: High | G23: In Progress | H23: Ayesha Khan | I23: 46323 | K23: =IF($B23="","",IFERROR(INDEX(Lists!$B$5:$B$7,MATCH($F23,Lists!$A$5:$A$7,0)),"")) -> 2 | L23: =IF(OR($B23="",$K23=""),"",WORKDAY($B23,$K23)) -> 46318 | M23: =IF(OR($B23="",$I23=""),"",IF($G23="Completed","",$I23-AsOf)) -> 2 | N23: =IF(OR($B23="",$J23=""),"",$J23-$B23) | O23: =IF($B23="","",IF($G23="Completed","",AsOf-$B23)) -> 5 | P23: =IF($B23="","",IF($G23="Completed",IF(AND($J23<>"",$J23>$I23),"Done (Late)","Done"),IF($I23="","No deadline",IF($I23<AsOf,"OVERDUE",IF($I23-AsOf<=Lists!$B$9,"Due Soon","On Track"))))) -> Due Soon | Q23: =IF(OR($B23="",$L23=""),"",IF($G23="Completed",IF($J23="","",IF($J23<=$L23,"Met","Missed")),IF(AsOf>$L23,"Breached","Within SLA"))) -> Breached | R23: =IF($B23="","",IF($G23="Completed",0,IFERROR(INDEX(Lists!$C$5:$C$7,MATCH($F23,Lists!$A$5:$A$7,0)),1)*IF($I23="",1,IF($I23<AsOf,3,IF($I23-AsOf<=Lists!$B$9,2,1))))) -> 6 | S23: =IF($B23="","",$R23+(1000-ROW())/100000) -> 6.00977 | T23: =IF($B23="","",IF(AND($G23="Completed",$J23=""),"Missing completion date",IF(AND($G23<>"Completed",$J23<>""),"Completion date on open request",IF(AND($I23<>"",$I23<$B23),"Deadline before raised","OK")))) -> OK
A24: DB-019 | B24: 46307 | C24: Risk | D24: Report | E24: Weekly suspicious activity summary | F24: Medium | G24: Completed | H24: Usman Tariq | I24: 46314 | J24: 46314 | K24: =IF($B24="","",IFERROR(INDEX(Lists!$B$5:$B$7,MATCH($F24,Lists!$A$5:$A$7,0)),"")) -> 5 | L24: =IF(OR($B24="",$K24=""),"",WORKDAY($B24,$K24)) -> 46314 | M24: =IF(OR($B24="",$I24=""),"",IF($G24="Completed","",$I24-AsOf)) | N24: =IF(OR($B24="",$J24=""),"",$J24-$B24) -> 7 | O24: =IF($B24="","",IF($G24="Completed","",AsOf-$B24)) | P24: =IF($B24="","",IF($G24="Completed",IF(AND($J24<>"",$J24>$I24),"Done (Late)","Done"),IF($I24="","No deadline",IF($I24<AsOf,"OVERDUE",IF($I24-AsOf<=Lists!$B$9,"Due Soon","On Track"))))) -> Done | Q24: =IF(OR($B24="",$L24=""),"",IF($G24="Completed",IF($J24="","",IF($J24<=$L24,"Met","Missed")),IF(AsOf>$L24,"Breached","Within SLA"))) -> Met | R24: =IF($B24="","",IF($G24="Completed",0,IFERROR(INDEX(Lists!$C$5:$C$7,MATCH($F24,Lists!$A$5:$A$7,0)),1)*IF($I24="",1,IF($I24<AsOf,3,IF($I24-AsOf<=Lists!$B$9,2,1))))) -> 0 | S24: =IF($B24="","",$R24+(1000-ROW())/100000) -> 0.00976 | T24: =IF($B24="","",IF(AND($G24="Completed",$J24=""),"Missing completion date",IF(AND($G24<>"Completed",$J24<>""),"Completion date on open request",IF(AND($I24<>"",$I24<$B24),"Deadline before raised","OK")))) -> OK
A25: DB-020 | B25: 46317 | C25: Finance | D25: Report | E25: Digital channel fee reconciliation | F25: High | G25: Pending | H25: Zainab Ali | I25: 46321 | K25: =IF($B25="","",IFERROR(INDEX(Lists!$B$5:$B$7,MATCH($F25,Lists!$A$5:$A$7,0)),"")) -> 2 | L25: =IF(OR($B25="",$K25=""),"",WORKDAY($B25,$K25)) -> 46321 | M25: =IF(OR($B25="",$I25=""),"",IF($G25="Completed","",$I25-AsOf)) -> 0 | N25: =IF(OR($B25="",$J25=""),"",$J25-$B25) | O25: =IF($B25="","",IF($G25="Completed","",AsOf-$B25)) -> 4 | P25: =IF($B25="","",IF($G25="Completed",IF(AND($J25<>"",$J25>$I25),"Done (Late)","Done"),IF($I25="","No deadline",IF($I25<AsOf,"OVERDUE",IF($I25-AsOf<=Lists!$B$9,"Due Soon","On Track"))))) -> Due Soon | Q25: =IF(OR($B25="",$L25=""),"",IF($G25="Completed",IF($J25="","",IF($J25<=$L25,"Met","Missed")),IF(AsOf>$L25,"Breached","Within SLA"))) -> Within SLA | R25: =IF($B25="","",IF($G25="Completed",0,IFERROR(INDEX(Lists!$C$5:$C$7,MATCH($F25,Lists!$A$5:$A$7,0)),1)*IF($I25="",1,IF($I25<AsOf,3,IF($I25-AsOf<=Lists!$B$9,2,1))))) -> 6 | S25: =IF($B25="","",$R25+(1000-ROW())/100000) -> 6.00975 | T25: =IF($B25="","",IF(AND($G25="Completed",$J25=""),"Missing completion date",IF(AND($G25<>"Completed",$J25<>""),"Completion date on open request",IF(AND($I25<>"",$I25<$B25),"Deadline before raised","OK")))) -> OK
A26: DB-021 | B26: 46308 | C26: Customer Support | D26: Incident Fix | E26: Mobile app crash complaint triage | F26: High | G26: Completed | H26: Fatima Noor | I26: 46311 | J26: 46311 | K26: =IF($B26="","",IFERROR(INDEX(Lists!$B$5:$B$7,MATCH($F26,Lists!$A$5:$A$7,0)),"")) -> 2 | L26: =IF(OR($B26="",$K26=""),"",WORKDAY($B26,$K26)) -> 46310 | M26: =IF(OR($B26="",$I26=""),"",IF($G26="Completed","",$I26-AsOf)) | N26: =IF(OR($B26="",$J26=""),"",$J26-$B26) -> 3 | O26: =IF($B26="","",IF($G26="Completed","",AsOf-$B26)) | P26: =IF($B26="","",IF($G26="Completed",IF(AND($J26<>"",$J26>$I26),"Done (Late)","Done"),IF($I26="","No deadline",IF($I26<AsOf,"OVERDUE",IF($I26-AsOf<=Lists!$B$9,"Due Soon","On Track"))))) -> Done | Q26: =IF(OR($B26="",$L26=""),"",IF($G26="Completed",IF($J26="","",IF($J26<=$L26,"Met","Missed")),IF(AsOf>$L26,"Breached","Within SLA"))) -> Missed | R26: =IF($B26="","",IF($G26="Completed",0,IFERROR(INDEX(Lists!$C$5:$C$7,MATCH($F26,Lists!$A$5:$A$7,0)),1)*IF($I26="",1,IF($I26<AsOf,3,IF($I26-AsOf<=Lists!$B$9,2,1))))) -> 0 | S26: =IF($B26="","",$R26+(1000-ROW())/100000) -> 0.00974 | T26: =IF($B26="","",IF(AND($G26="Completed",$J26=""),"Missing completion date",IF(AND($G26<>"Completed",$J26<>""),"Completion date on open request",IF(AND($I26<>"",$I26<$B26),"Deadline before raised","OK")))) -> OK
A27: DB-022 | B27: 46309 | C27: Marketing | D27: Change Request | E27: Update app store screenshots | F27: Low | G27: Pending | H27: Omar Siddiqui | I27: 46318 | K27: =IF($B27="","",IFERROR(INDEX(Lists!$B$5:$B$7,MATCH($F27,Lists!$A$5:$A$7,0)),"")) -> 8 | L27: =IF(OR($B27="",$K27=""),"",WORKDAY($B27,$K27)) -> 46321 | M27: =IF(OR($B27="",$I27=""),"",IF($G27="Completed","",$I27-AsOf)) -> -3 | N27: =IF(OR($B27="",$J27=""),"",$J27-$B27) | O27: =IF($B27="","",IF($G27="Completed","",AsOf-$B27)) -> 12 | P27: =IF($B27="","",IF($G27="Completed",IF(AND($J27<>"",$J27>$I27),"Done (Late)","Done"),IF($I27="","No deadline",IF($I27<AsOf,"OVERDUE",IF($I27-AsOf<=Lists!$B$9,"Due Soon","On Track"))))) -> OVERDUE | Q27: =IF(OR($B27="",$L27=""),"",IF($G27="Completed",IF($J27="","",IF($J27<=$L27,"Met","Missed")),IF(AsOf>$L27,"Breached","Within SLA"))) -> Within SLA | R27: =IF($B27="","",IF($G27="Completed",0,IFERROR(INDEX(Lists!$C$5:$C$7,MATCH($F27,Lists!$A$5:$A$7,0)),1)*IF($I27="",1,IF($I27<AsOf,3,IF($I27-AsOf<=Lists!$B$9,2,1))))) -> 3 | S27: =IF($B27="","",$R27+(1000-ROW())/100000) -> 3.00973 | T27: =IF($B27="","",IF(AND($G27="Completed",$J27=""),"Missing completion date",IF(AND($G27<>"Completed",$J27<>""),"Completion date on open request",IF(AND($I27<>"",$I27<$B27),"Deadline before raised","OK")))) -> OK
A28: DB-023 | B28: 46303 | C28: IT | D28: Access Request | E28: Test environment access for UAT team | F28: Medium | G28: Completed | H28: Hamza Malik | I28: 46308 | J28: 46307 | K28: =IF($B28="","",IFERROR(INDEX(Lists!$B$5:$B$7,MATCH($F28,Lists!$A$5:$A$7,0)),"")) -> 5 | L28: =IF(OR($B28="",$K28=""),"",WORKDAY($B28,$K28)) -> 46310 | M28: =IF(OR($B28="",$I28=""),"",IF($G28="Completed","",$I28-AsOf)) | N28: =IF(OR($B28="",$J28=""),"",$J28-$B28) -> 4 | O28: =IF($B28="","",IF($G28="Completed","",AsOf-$B28)) | P28: =IF($B28="","",IF($G28="Completed",IF(AND($J28<>"",$J28>$I28),"Done (Late)","Done"),IF($I28="","No deadline",IF($I28<AsOf,"OVERDUE",IF($I28-AsOf<=Lists!$B$9,"Due Soon","On Track"))))) -> Done | Q28: =IF(OR($B28="",$L28=""),"",IF($G28="Completed",IF($J28="","",IF($J28<=$L28,"Met","Missed")),IF(AsOf>$L28,"Breached","Within SLA"))) -> Met | R28: =IF($B28="","",IF($G28="Completed",0,IFERROR(INDEX(Lists!$C$5:$C$7,MATCH($F28,Lists!$A$5:$A$7,0)),1)*IF($I28="",1,IF($I28<AsOf,3,IF($I28-AsOf<=Lists!$B$9,2,1))))) -> 0 | S28: =IF($B28="","",$R28+(1000-ROW())/100000) -> 0.00972 | T28: =IF($B28="","",IF(AND($G28="Completed",$J28=""),"Missing completion date",IF(AND($G28<>"Completed",$J28<>""),"Completion date on open request",IF(AND($I28<>"",$I28<$B28),"Deadline before raised","OK")))) -> OK
A29: DB-024 | B29: 46304 | C29: Operations | D29: Documentation | E29: Branch operations SOP update | F29: Low | G29: In Progress | H29: Sana Raza | I29: 46315 | K29: =IF($B29="","",IFERROR(INDEX(Lists!$B$5:$B$7,MATCH($F29,Lists!$A$5:$A$7,0)),"")) -> 8 | L29: =IF(OR($B29="",$K29=""),"",WORKDAY($B29,$K29)) -> 46316 | M29: =IF(OR($B29="",$I29=""),"",IF($G29="Completed","",$I29-AsOf)) -> -6 | N29: =IF(OR($B29="",$J29=""),"",$J29-$B29) | O29: =IF($B29="","",IF($G29="Completed","",AsOf-$B29)) -> 17 | P29: =IF($B29="","",IF($G29="Completed",IF(AND($J29<>"",$J29>$I29),"Done (Late)","Done"),IF($I29="","No deadline",IF($I29<AsOf,"OVERDUE",IF($I29-AsOf<=Lists!$B$9,"Due Soon","On Track"))))) -> OVERDUE | Q29: =IF(OR($B29="",$L29=""),"",IF($G29="Completed",IF($J29="","",IF($J29<=$L29,"Met","Missed")),IF(AsOf>$L29,"Breached","Within SLA"))) -> Breached | R29: =IF($B29="","",IF($G29="Completed",0,IFERROR(INDEX(Lists!$C$5:$C$7,MATCH($F29,Lists!$A$5:$A$7,0)),1)*IF($I29="",1,IF($I29<AsOf,3,IF($I29-AsOf<=Lists!$B$9,2,1))))) -> 3 | S29: =IF($B29="","",$R29+(1000-ROW())/100000) -> 3.00971 | T29: =IF($B29="","",IF(AND($G29="Completed",$J29=""),"Missing completion date",IF(AND($G29<>"Completed",$J29<>""),"Completion date on open request",IF(AND($I29<>"",$I29<$B29),"Deadline before raised","OK")))) -> OK
A30: DB-025 | B30: 46300 | C30: Compliance | D30: Report | E30: Monthly AML metrics report | F30: Medium | G30: Completed | H30: Bilal Ahmed | I30: 46307 | J30: 46307 | K30: =IF($B30="","",IFERROR(INDEX(Lists!$B$5:$B$7,MATCH($F30,Lists!$A$5:$A$7,0)),"")) -> 5 | L30: =IF(OR($B30="",$K30=""),"",WORKDAY($B30,$K30)) -> 46307 | M30: =IF(OR($B30="",$I30=""),"",IF($G30="Completed","",$I30-AsOf)) | N30: =IF(OR($B30="",$J30=""),"",$J30-$B30) -> 7 | O30: =IF($B30="","",IF($G30="Completed","",AsOf-$B30)) | P30: =IF($B30="","",IF($G30="Completed",IF(AND($J30<>"",$J30>$I30),"Done (Late)","Done"),IF($I30="","No deadline",IF($I30<AsOf,"OVERDUE",IF($I30-AsOf<=Lists!$B$9,"Due Soon","On Track"))))) -> Done | Q30: =IF(OR($B30="",$L30=""),"",IF($G30="Completed",IF($J30="","",IF($J30<=$L30,"Met","Missed")),IF(AsOf>$L30,"Breached","Within SLA"))) -> Met | R30: =IF($B30="","",IF($G30="Completed",0,IFERROR(INDEX(Lists!$C$5:$C$7,MATCH($F30,Lists!$A$5:$A$7,0)),1)*IF($I30="",1,IF($I30<AsOf,3,IF($I30-AsOf<=Lists!$B$9,2,1))))) -> 0 | S30: =IF($B30="","",$R30+(1000-ROW())/100000) -> 0.0097 | T30: =IF($B30="","",IF(AND($G30="Completed",$J30=""),"Missing completion date",IF(AND($G30<>"Completed",$J30<>""),"Completion date on open request",IF(AND($I30<>"",$I30<$B30),"Deadline before raised","OK")))) -> OK
A31: DB-026 | B31: 46301 | C31: Digital Banking | D31: Testing Support | E31: Regression testing for bill payment | F31: High | G31: Completed | H31: Omar Siddiqui | I31: 46304 | J31: 46303 | K31: =IF($B31="","",IFERROR(INDEX(Lists!$B$5:$B$7,MATCH($F31,Lists!$A$5:$A$7,0)),"")) -> 2 | L31: =IF(OR($B31="",$K31=""),"",WORKDAY($B31,$K31)) -> 46303 | M31: =IF(OR($B31="",$I31=""),"",IF($G31="Completed","",$I31-AsOf)) | N31: =IF(OR($B31="",$J31=""),"",$J31-$B31) -> 2 | O31: =IF($B31="","",IF($G31="Completed","",AsOf-$B31)) | P31: =IF($B31="","",IF($G31="Completed",IF(AND($J31<>"",$J31>$I31),"Done (Late)","Done"),IF($I31="","No deadline",IF($I31<AsOf,"OVERDUE",IF($I31-AsOf<=Lists!$B$9,"Due Soon","On Track"))))) -> Done | Q31: =IF(OR($B31="",$L31=""),"",IF($G31="Completed",IF($J31="","",IF($J31<=$L31,"Met","Missed")),IF(AsOf>$L31,"Breached","Within SLA"))) -> Met | R31: =IF($B31="","",IF($G31="Completed",0,IFERROR(INDEX(Lists!$C$5:$C$7,MATCH($F31,Lists!$A$5:$A$7,0)),1)*IF($I31="",1,IF($I31<AsOf,3,IF($I31-AsOf<=Lists!$B$9,2,1))))) -> 0 | S31: =IF($B31="","",$R31+(1000-ROW())/100000) -> 0.00969 | T31: =IF($B31="","",IF(AND($G31="Completed",$J31=""),"Missing completion date",IF(AND($G31<>"Completed",$J31<>""),"Completion date on open request",IF(AND($I31<>"",$I31<$B31),"Deadline before raised","OK")))) -> OK
A32: DB-027 | B32: 46296 | C32: Finance | D32: Documentation | E32: Budget note for digital initiatives | F32: Low | G32: Completed | H32: Zainab Ali | I32: 46310 | J32: 46309 | K32: =IF($B32="","",IFERROR(INDEX(Lists!$B$5:$B$7,MATCH($F32,Lists!$A$5:$A$7,0)),"")) -> 8 | L32: =IF(OR($B32="",$K32=""),"",WORKDAY($B32,$K32)) -> 46308 | M32: =IF(OR($B32="",$I32=""),"",IF($G32="Completed","",$I32-AsOf)) | N32: =IF(OR($B32="",$J32=""),"",$J32-$B32) -> 13 | O32: =IF($B32="","",IF($G32="Completed","",AsOf-$B32)) | P32: =IF($B32="","",IF($G32="Completed",IF(AND($J32<>"",$J32>$I32),"Done (Late)","Done"),IF($I32="","No deadline",IF($I32<AsOf,"OVERDUE",IF($I32-AsOf<=Lists!$B$9,"Due Soon","On Track"))))) -> Done | Q32: =IF(OR($B32="",$L32=""),"",IF($G32="Completed",IF($J32="","",IF($J32<=$L32,"Met","Missed")),IF(AsOf>$L32,"Breached","Within SLA"))) -> Missed | R32: =IF($B32="","",IF($G32="Completed",0,IFERROR(INDEX(Lists!$C$5:$C$7,MATCH($F32,Lists!$A$5:$A$7,0)),1)*IF($I32="",1,IF($I32<AsOf,3,IF($I32-AsOf<=Lists!$B$9,2,1))))) -> 0 | S32: =IF($B32="","",$R32+(1000-ROW())/100000) -> 0.00968 | T32: =IF($B32="","",IF(AND($G32="Completed",$J32=""),"Missing completion date",IF(AND($G32<>"Completed",$J32<>""),"Completion date on open request",IF(AND($I32<>"",$I32<$B32),"Deadline before raised","OK")))) -> OK
A33: DB-028 | B33: 46318 | C33: Risk | D33: Change Request | E33: Transaction limit rule change | F33: High | G33: In Progress | H33: Usman Tariq | I33: 46323 | K33: =IF($B33="","",IFERROR(INDEX(Lists!$B$5:$B$7,MATCH($F33,Lists!$A$5:$A$7,0)),"")) -> 2 | L33: =IF(OR($B33="",$K33=""),"",WORKDAY($B33,$K33)) -> 46322 | M33: =IF(OR($B33="",$I33=""),"",IF($G33="Completed","",$I33-AsOf)) -> 2 | N33: =IF(OR($B33="",$J33=""),"",$J33-$B33) | O33: =IF($B33="","",IF($G33="Completed","",AsOf-$B33)) -> 3 | P33: =IF($B33="","",IF($G33="Completed",IF(AND($J33<>"",$J33>$I33),"Done (Late)","Done"),IF($I33="","No deadline",IF($I33<AsOf,"OVERDUE",IF($I33-AsOf<=Lists!$B$9,"Due Soon","On Track"))))) -> Due Soon | Q33: =IF(OR($B33="",$L33=""),"",IF($G33="Completed",IF($J33="","",IF($J33<=$L33,"Met","Missed")),IF(AsOf>$L33,"Breached","Within SLA"))) -> Within SLA | R33: =IF($B33="","",IF($G33="Completed",0,IFERROR(INDEX(Lists!$C$5:$C$7,MATCH($F33,Lists!$A$5:$A$7,0)),1)*IF($I33="",1,IF($I33<AsOf,3,IF($I33-AsOf<=Lists!$B$9,2,1))))) -> 6 | S33: =IF($B33="","",$R33+(1000-ROW())/100000) -> 6.00967 | T33: =IF($B33="","",IF(AND($G33="Completed",$J33=""),"Missing completion date",IF(AND($G33<>"Completed",$J33<>""),"Completion date on open request",IF(AND($I33<>"",$I33<$B33),"Deadline before raised","OK")))) -> OK
A34: DB-029 | B34: 46317 | C34: Customer Support | D34: Documentation | E34: Chatbot response script review | F34: Medium | G34: Pending | H34: Ayesha Khan | I34: 46325 | K34: =IF($B34="","",IFERROR(INDEX(Lists!$B$5:$B$7,MATCH($F34,Lists!$A$5:$A$7,0)),"")) -> 5 | L34: =IF(OR($B34="",$K34=""),"",WORKDAY($B34,$K34)) -> 46324 | M34: =IF(OR($B34="",$I34=""),"",IF($G34="Completed","",$I34-AsOf)) -> 4 | N34: =IF(OR($B34="",$J34=""),"",$J34-$B34) | O34: =IF($B34="","",IF($G34="Completed","",AsOf-$B34)) -> 4 | P34: =IF($B34="","",IF($G34="Completed",IF(AND($J34<>"",$J34>$I34),"Done (Late)","Done"),IF($I34="","No deadline",IF($I34<AsOf,"OVERDUE",IF($I34-AsOf<=Lists!$B$9,"Due Soon","On Track"))))) -> On Track | Q34: =IF(OR($B34="",$L34=""),"",IF($G34="Completed",IF($J34="","",IF($J34<=$L34,"Met","Missed")),IF(AsOf>$L34,"Breached","Within SLA"))) -> Within SLA | R34: =IF($B34="","",IF($G34="Completed",0,IFERROR(INDEX(Lists!$C$5:$C$7,MATCH($F34,Lists!$A$5:$A$7,0)),1)*IF($I34="",1,IF($I34<AsOf,3,IF($I34-AsOf<=Lists!$B$9,2,1))))) -> 2 | S34: =IF($B34="","",$R34+(1000-ROW())/100000) -> 2.00966 | T34: =IF($B34="","",IF(AND($G34="Completed",$J34=""),"Missing completion date",IF(AND($G34<>"Completed",$J34<>""),"Completion date on open request",IF(AND($I34<>"",$I34<$B34),"Deadline before raised","OK")))) -> OK
A35: DB-030 | B35: 46302 | C35: IT | D35: Incident Fix | E35: SMS gateway delay investigation | F35: High | G35: Completed | H35: Hamza Malik | I35: 46304 | J35: 46304 | K35: =IF($B35="","",IFERROR(INDEX(Lists!$B$5:$B$7,MATCH($F35,Lists!$A$5:$A$7,0)),"")) -> 2 | L35: =IF(OR($B35="",$K35=""),"",WORKDAY($B35,$K35)) -> 46304 | M35: =IF(OR($B35="",$I35=""),"",IF($G35="Completed","",$I35-AsOf)) | N35: =IF(OR($B35="",$J35=""),"",$J35-$B35) -> 2 | O35: =IF($B35="","",IF($G35="Completed","",AsOf-$B35)) | P35: =IF($B35="","",IF($G35="Completed",IF(AND($J35<>"",$J35>$I35),"Done (Late)","Done"),IF($I35="","No deadline",IF($I35<AsOf,"OVERDUE",IF($I35-AsOf<=Lists!$B$9,"Due Soon","On Track"))))) -> Done | Q35: =IF(OR($B35="",$L35=""),"",IF($G35="Completed",IF($J35="","",IF($J35<=$L35,"Met","Missed")),IF(AsOf>$L35,"Breached","Within SLA"))) -> Met | R35: =IF($B35="","",IF($G35="Completed",0,IFERROR(INDEX(Lists!$C$5:$C$7,MATCH($F35,Lists!$A$5:$A$7,0)),1)*IF($I35="",1,IF($I35<AsOf,3,IF($I35-AsOf<=Lists!$B$9,2,1))))) -> 0 | S35: =IF($B35="","",$R35+(1000-ROW())/100000) -> 0.00965 | T35: =IF($B35="","",IF(AND($G35="Completed",$J35=""),"Missing completion date",IF(AND($G35<>"Completed",$J35<>""),"Completion date on open request",IF(AND($I35<>"",$I35<$B35),"Deadline before raised","OK")))) -> OK
A36: DB-031 | B36: 46321 | C36: Operations | D36: Change Request | E36: Update cut-off time settings | F36: Medium | G36: Pending | H36: Sana Raza | I36: 46329 | K36: =IF($B36="","",IFERROR(INDEX(Lists!$B$5:$B$7,MATCH($F36,Lists!$A$5:$A$7,0)),"")) -> 5 | L36: =IF(OR($B36="",$K36=""),"",WORKDAY($B36,$K36)) -> 46328 | M36: =IF(OR($B36="",$I36=""),"",IF($G36="Completed","",$I36-AsOf)) -> 8 | N36: =IF(OR($B36="",$J36=""),"",$J36-$B36) | O36: =IF($B36="","",IF($G36="Completed","",AsOf-$B36)) -> 0 | P36: =IF($B36="","",IF($G36="Completed",IF(AND($J36<>"",$J36>$I36),"Done (Late)","Done"),IF($I36="","No deadline",IF($I36<AsOf,"OVERDUE",IF($I36-AsOf<=Lists!$B$9,"Due Soon","On Track"))))) -> On Track | Q36: =IF(OR($B36="",$L36=""),"",IF($G36="Completed",IF($J36="","",IF($J36<=$L36,"Met","Missed")),IF(AsOf>$L36,"Breached","Within SLA"))) -> Within SLA | R36: =IF($B36="","",IF($G36="Completed",0,IFERROR(INDEX(Lists!$C$5:$C$7,MATCH($F36,Lists!$A$5:$A$7,0)),1)*IF($I36="",1,IF($I36<AsOf,3,IF($I36-AsOf<=Lists!$B$9,2,1))))) -> 2 | S36: =IF($B36="","",$R36+(1000-ROW())/100000) -> 2.00964 | T36: =IF($B36="","",IF(AND($G36="Completed",$J36=""),"Missing completion date",IF(AND($G36<>"Completed",$J36<>""),"Completion date on open request",IF(AND($I36<>"",$I36<$B36),"Deadline before raised","OK")))) -> OK
A37: DB-032 | B37: 46321 | C37: Digital Banking | D37: Testing Support | E37: Accessibility testing for mobile app | F37: Medium | G37: Pending | H37: Omar Siddiqui | I37: 46331 | K37: =IF($B37="","",IFERROR(INDEX(Lists!$B$5:$B$7,MATCH($F37,Lists!$A$5:$A$7,0)),"")) -> 5 | L37: =IF(OR($B37="",$K37=""),"",WORKDAY($B37,$K37)) -> 46328 | M37: =IF(OR($B37="",$I37=""),"",IF($G37="Completed","",$I37-AsOf)) -> 10 | N37: =IF(OR($B37="",$J37=""),"",$J37-$B37) | O37: =IF($B37="","",IF($G37="Completed","",AsOf-$B37)) -> 0 | P37: =IF($B37="","",IF($G37="Completed",IF(AND($J37<>"",$J37>$I37),"Done (Late)","Done"),IF($I37="","No deadline",IF($I37<AsOf,"OVERDUE",IF($I37-AsOf<=Lists!$B$9,"Due Soon","On Track"))))) -> On Track | Q37: =IF(OR($B37="",$L37=""),"",IF($G37="Completed",IF($J37="","",IF($J37<=$L37,"Met","Missed")),IF(AsOf>$L37,"Breached","Within SLA"))) -> Within SLA | R37: =IF($B37="","",IF($G37="Completed",0,IFERROR(INDEX(Lists!$C$5:$C$7,MATCH($F37,Lists!$A$5:$A$7,0)),1)*IF($I37="",1,IF($I37<AsOf,3,IF($I37-AsOf<=Lists!$B$9,2,1))))) -> 2 | S37: =IF($B37="","",$R37+(1000-ROW())/100000) -> 2.00963 | T37: =IF($B37="","",IF(AND($G37="Completed",$J37=""),"Missing completion date",IF(AND($G37<>"Completed",$J37<>""),"Completion date on open request",IF(AND($I37<>"",$I37<$B37),"Deadline before raised","OK")))) -> OK
A38: DB-033 | B38: 46309 | C38: Compliance | D38: Access Request | E38: Auditor read-only dashboard access | F38: Medium | G38: Completed | H38: Hamza Malik | I38: 46316 | J38: 46315 | K38: =IF($B38="","",IFERROR(INDEX(Lists!$B$5:$B$7,MATCH($F38,Lists!$A$5:$A$7,0)),"")) -> 5 | L38: =IF(OR($B38="",$K38=""),"",WORKDAY($B38,$K38)) -> 46316 | M38: =IF(OR($B38="",$I38=""),"",IF($G38="Completed","",$I38-AsOf)) | N38: =IF(OR($B38="",$J38=""),"",$J38-$B38) -> 6 | O38: =IF($B38="","",IF($G38="Completed","",AsOf-$B38)) | P38: =IF($B38="","",IF($G38="Completed",IF(AND($J38<>"",$J38>$I38),"Done (Late)","Done"),IF($I38="","No deadline",IF($I38<AsOf,"OVERDUE",IF($I38-AsOf<=Lists!$B$9,"Due Soon","On Track"))))) -> Done | Q38: =IF(OR($B38="",$L38=""),"",IF($G38="Completed",IF($J38="","",IF($J38<=$L38,"Met","Missed")),IF(AsOf>$L38,"Breached","Within SLA"))) -> Met | R38: =IF($B38="","",IF($G38="Completed",0,IFERROR(INDEX(Lists!$C$5:$C$7,MATCH($F38,Lists!$A$5:$A$7,0)),1)*IF($I38="",1,IF($I38<AsOf,3,IF($I38-AsOf<=Lists!$B$9,2,1))))) -> 0 | S38: =IF($B38="","",$R38+(1000-ROW())/100000) -> 0.00962 | T38: =IF($B38="","",IF(AND($G38="Completed",$J38=""),"Missing completion date",IF(AND($G38<>"Completed",$J38<>""),"Completion date on open request",IF(AND($I38<>"",$I38<$B38),"Deadline before raised","OK")))) -> OK
A39: DB-034 | B39: 46297 | C39: Marketing | D39: Report | E39: Campaign performance snapshot | F39: Low | G39: Completed | H39: Zainab Ali | I39: 46309 | J39: 46310 | K39: =IF($B39="","",IFERROR(INDEX(Lists!$B$5:$B$7,MATCH($F39,Lists!$A$5:$A$7,0)),"")) -> 8 | L39: =IF(OR($B39="",$K39=""),"",WORKDAY($B39,$K39)) -> 46309 | M39: =IF(OR($B39="",$I39=""),"",IF($G39="Completed","",$I39-AsOf)) | N39: =IF(OR($B39="",$J39=""),"",$J39-$B39) -> 13 | O39: =IF($B39="","",IF($G39="Completed","",AsOf-$B39)) | P39: =IF($B39="","",IF($G39="Completed",IF(AND($J39<>"",$J39>$I39),"Done (Late)","Done"),IF($I39="","No deadline",IF($I39<AsOf,"OVERDUE",IF($I39-AsOf<=Lists!$B$9,"Due Soon","On Track"))))) -> Done (Late) | Q39: =IF(OR($B39="",$L39=""),"",IF($G39="Completed",IF($J39="","",IF($J39<=$L39,"Met","Missed")),IF(AsOf>$L39,"Breached","Within SLA"))) -> Missed | R39: =IF($B39="","",IF($G39="Completed",0,IFERROR(INDEX(Lists!$C$5:$C$7,MATCH($F39,Lists!$A$5:$A$7,0)),1)*IF($I39="",1,IF($I39<AsOf,3,IF($I39-AsOf<=Lists!$B$9,2,1))))) -> 0 | S39: =IF($B39="","",$R39+(1000-ROW())/100000) -> 0.00961 | T39: =IF($B39="","",IF(AND($G39="Completed",$J39=""),"Missing completion date",IF(AND($G39<>"Completed",$J39<>""),"Completion date on open request",IF(AND($I39<>"",$I39<$B39),"Deadline before raised","OK")))) -> OK
A40: DB-035 | B40: 46311 | C40: Finance | D40: Compliance Review | E40: Vendor payment control review | F40: Medium | G40: In Progress | H40: Bilal Ahmed | I40: 46322 | K40: =IF($B40="","",IFERROR(INDEX(Lists!$B$5:$B$7,MATCH($F40,Lists!$A$5:$A$7,0)),"")) -> 5 | L40: =IF(OR($B40="",$K40=""),"",WORKDAY($B40,$K40)) -> 46318 | M40: =IF(OR($B40="",$I40=""),"",IF($G40="Completed","",$I40-AsOf)) -> 1 | N40: =IF(OR($B40="",$J40=""),"",$J40-$B40) | O40: =IF($B40="","",IF($G40="Completed","",AsOf-$B40)) -> 10 | P40: =IF($B40="","",IF($G40="Completed",IF(AND($J40<>"",$J40>$I40),"Done (Late)","Done"),IF($I40="","No deadline",IF($I40<AsOf,"OVERDUE",IF($I40-AsOf<=Lists!$B$9,"Due Soon","On Track"))))) -> Due Soon | Q40: =IF(OR($B40="",$L40=""),"",IF($G40="Completed",IF($J40="","",IF($J40<=$L40,"Met","Missed")),IF(AsOf>$L40,"Breached","Within SLA"))) -> Breached | R40: =IF($B40="","",IF($G40="Completed",0,IFERROR(INDEX(Lists!$C$5:$C$7,MATCH($F40,Lists!$A$5:$A$7,0)),1)*IF($I40="",1,IF($I40<AsOf,3,IF($I40-AsOf<=Lists!$B$9,2,1))))) -> 4 | S40: =IF($B40="","",$R40+(1000-ROW())/100000) -> 4.0096 | T40: =IF($B40="","",IF(AND($G40="Completed",$J40=""),"Missing completion date",IF(AND($G40<>"Completed",$J40<>""),"Completion date on open request",IF(AND($I40<>"",$I40<$B40),"Deadline before raised","OK")))) -> OK
A41: DB-036 | B41: 46318 | C41: Risk | D41: Access Request | E41: Fraud tool admin access | F41: High | G41: Pending | H41: Hamza Malik | I41: 46322 | K41: =IF($B41="","",IFERROR(INDEX(Lists!$B$5:$B$7,MATCH($F41,Lists!$A$5:$A$7,0)),"")) -> 2 | L41: =IF(OR($B41="",$K41=""),"",WORKDAY($B41,$K41)) -> 46322 | M41: =IF(OR($B41="",$I41=""),"",IF($G41="Completed","",$I41-AsOf)) -> 1 | N41: =IF(OR($B41="",$J41=""),"",$J41-$B41) | O41: =IF($B41="","",IF($G41="Completed","",AsOf-$B41)) -> 3 | P41: =IF($B41="","",IF($G41="Completed",IF(AND($J41<>"",$J41>$I41),"Done (Late)","Done"),IF($I41="","No deadline",IF($I41<AsOf,"OVERDUE",IF($I41-AsOf<=Lists!$B$9,"Due Soon","On Track"))))) -> Due Soon | Q41: =IF(OR($B41="",$L41=""),"",IF($G41="Completed",IF($J41="","",IF($J41<=$L41,"Met","Missed")),IF(AsOf>$L41,"Breached","Within SLA"))) -> Within SLA | R41: =IF($B41="","",IF($G41="Completed",0,IFERROR(INDEX(Lists!$C$5:$C$7,MATCH($F41,Lists!$A$5:$A$7,0)),1)*IF($I41="",1,IF($I41<AsOf,3,IF($I41-AsOf<=Lists!$B$9,2,1))))) -> 6 | S41: =IF($B41="","",$R41+(1000-ROW())/100000) -> 6.00959 | T41: =IF($B41="","",IF(AND($G41="Completed",$J41=""),"Missing completion date",IF(AND($G41<>"Completed",$J41<>""),"Completion date on open request",IF(AND($I41<>"",$I41<$B41),"Deadline before raised","OK")))) -> OK
A42: DB-037 | B42: 46316 | C42: Customer Support | D42: Incident Fix | E42: Login error escalation log | F42: Medium | G42: In Progress | H42: Ayesha Khan | I42: 46323 | K42: =IF($B42="","",IFERROR(INDEX(Lists!$B$5:$B$7,MATCH($F42,Lists!$A$5:$A$7,0)),"")) -> 5 | L42: =IF(OR($B42="",$K42=""),"",WORKDAY($B42,$K42)) -> 46323 | M42: =IF(OR($B42="",$I42=""),"",IF($G42="Completed","",$I42-AsOf)) -> 2 | N42: =IF(OR($B42="",$J42=""),"",$J42-$B42) | O42: =IF($B42="","",IF($G42="Completed","",AsOf-$B42)) -> 5 | P42: =IF($B42="","",IF($G42="Completed",IF(AND($J42<>"",$J42>$I42),"Done (Late)","Done"),IF($I42="","No deadline",IF($I42<AsOf,"OVERDUE",IF($I42-AsOf<=Lists!$B$9,"Due Soon","On Track"))))) -> Due Soon | Q42: =IF(OR($B42="",$L42=""),"",IF($G42="Completed",IF($J42="","",IF($J42<=$L42,"Met","Missed")),IF(AsOf>$L42,"Breached","Within SLA"))) -> Within SLA | R42: =IF($B42="","",IF($G42="Completed",0,IFERROR(INDEX(Lists!$C$5:$C$7,MATCH($F42,Lists!$A$5:$A$7,0)),1)*IF($I42="",1,IF($I42<AsOf,3,IF($I42-AsOf<=Lists!$B$9,2,1))))) -> 4 | S42: =IF($B42="","",$R42+(1000-ROW())/100000) -> 4.00958 | T42: =IF($B42="","",IF(AND($G42="Completed",$J42=""),"Missing completion date",IF(AND($G42<>"Completed",$J42<>""),"Completion date on open request",IF(AND($I42<>"",$I42<$B42),"Deadline before raised","OK")))) -> OK
A43: DB-038 | B43: 46321 | C43: Operations | D43: Report | E43: Month-end digital volume report | F43: High | G43: Pending | H43: Sana Raza | I43: 46325 | K43: =IF($B43="","",IFERROR(INDEX(Lists!$B$5:$B$7,MATCH($F43,Lists!$A$5:$A$7,0)),"")) -> 2 | L43: =IF(OR($B43="",$K43=""),"",WORKDAY($B43,$K43)) -> 46323 | M43: =IF(OR($B43="",$I43=""),"",IF($G43="Completed","",$I43-AsOf)) -> 4 | N43: =IF(OR($B43="",$J43=""),"",$J43-$B43) | O43: =IF($B43="","",IF($G43="Completed","",AsOf-$B43)) -> 0 | P43: =IF($B43="","",IF($G43="Completed",IF(AND($J43<>"",$J43>$I43),"Done (Late)","Done"),IF($I43="","No deadline",IF($I43<AsOf,"OVERDUE",IF($I43-AsOf<=Lists!$B$9,"Due Soon","On Track"))))) -> On Track | Q43: =IF(OR($B43="",$L43=""),"",IF($G43="Completed",IF($J43="","",IF($J43<=$L43,"Met","Missed")),IF(AsOf>$L43,"Breached","Within SLA"))) -> Within SLA | R43: =IF($B43="","",IF($G43="Completed",0,IFERROR(INDEX(Lists!$C$5:$C$7,MATCH($F43,Lists!$A$5:$A$7,0)),1)*IF($I43="",1,IF($I43<AsOf,3,IF($I43-AsOf<=Lists!$B$9,2,1))))) -> 3 | S43: =IF($B43="","",$R43+(1000-ROW())/100000) -> 3.00957 | T43: =IF($B43="","",IF(AND($G43="Completed",$J43=""),"Missing completion date",IF(AND($G43<>"Completed",$J43<>""),"Completion date on open request",IF(AND($I43<>"",$I43<$B43),"Deadline before raised","OK")))) -> OK
A44: DB-039 | B44: 46314 | C44: Digital Banking | D44: Documentation | E44: Release notes for app v2.4 | F44: Low | G44: In Progress | H44: Omar Siddiqui | I44: 46328 | K44: =IF($B44="","",IFERROR(INDEX(Lists!$B$5:$B$7,MATCH($F44,Lists!$A$5:$A$7,0)),"")) -> 8 | L44: =IF(OR($B44="",$K44=""),"",WORKDAY($B44,$K44)) -> 46324 | M44: =IF(OR($B44="",$I44=""),"",IF($G44="Completed","",$I44-AsOf)) -> 7 | N44: =IF(OR($B44="",$J44=""),"",$J44-$B44) | O44: =IF($B44="","",IF($G44="Completed","",AsOf-$B44)) -> 7 | P44: =IF($B44="","",IF($G44="Completed",IF(AND($J44<>"",$J44>$I44),"Done (Late)","Done"),IF($I44="","No deadline",IF($I44<AsOf,"OVERDUE",IF($I44-AsOf<=Lists!$B$9,"Due Soon","On Track"))))) -> On Track | Q44: =IF(OR($B44="",$L44=""),"",IF($G44="Completed",IF($J44="","",IF($J44<=$L44,"Met","Missed")),IF(AsOf>$L44,"Breached","Within SLA"))) -> Within SLA | R44: =IF($B44="","",IF($G44="Completed",0,IFERROR(INDEX(Lists!$C$5:$C$7,MATCH($F44,Lists!$A$5:$A$7,0)),1)*IF($I44="",1,IF($I44<AsOf,3,IF($I44-AsOf<=Lists!$B$9,2,1))))) -> 1 | S44: =IF($B44="","",$R44+(1000-ROW())/100000) -> 1.00956 | T44: =IF($B44="","",IF(AND($G44="Completed",$J44=""),"Missing completion date",IF(AND($G44<>"Completed",$J44<>""),"Completion date on open request",IF(AND($I44<>"",$I44<$B44),"Deadline before raised","OK")))) -> OK
A45: DB-040 | B45: 46296 | C45: IT | D45: Change Request | E45: Server patch window schedule | F45: Medium | G45: Completed | H45: Hamza Malik | I45: 46304 | J45: 46303 | K45: =IF($B45="","",IFERROR(INDEX(Lists!$B$5:$B$7,MATCH($F45,Lists!$A$5:$A$7,0)),"")) -> 5 | L45: =IF(OR($B45="",$K45=""),"",WORKDAY($B45,$K45)) -> 46303 | M45: =IF(OR($B45="",$I45=""),"",IF($G45="Completed","",$I45-AsOf)) | N45: =IF(OR($B45="",$J45=""),"",$J45-$B45) -> 7 | O45: =IF($B45="","",IF($G45="Completed","",AsOf-$B45)) | P45: =IF($B45="","",IF($G45="Completed",IF(AND($J45<>"",$J45>$I45),"Done (Late)","Done"),IF($I45="","No deadline",IF($I45<AsOf,"OVERDUE",IF($I45-AsOf<=Lists!$B$9,"Due Soon","On Track"))))) -> Done | Q45: =IF(OR($B45="",$L45=""),"",IF($G45="Completed",IF($J45="","",IF($J45<=$L45,"Met","Missed")),IF(AsOf>$L45,"Breached","Within SLA"))) -> Met | R45: =IF($B45="","",IF($G45="Completed",0,IFERROR(INDEX(Lists!$C$5:$C$7,MATCH($F45,Lists!$A$5:$A$7,0)),1)*IF($I45="",1,IF($I45<AsOf,3,IF($I45-AsOf<=Lists!$B$9,2,1))))) -> 0 | S45: =IF($B45="","",$R45+(1000-ROW())/100000) -> 0.00955 | T45: =IF($B45="","",IF(AND($G45="Completed",$J45=""),"Missing completion date",IF(AND($G45<>"Completed",$J45<>""),"Completion date on open request",IF(AND($I45<>"",$I45<$B45),"Deadline before raised","OK")))) -> OK
A46: DB-041 | K46: =IF($B46="","",IFERROR(INDEX(Lists!$B$5:$B$7,MATCH($F46,Lists!$A$5:$A$7,0)),"")) | L46: =IF(OR($B46="",$K46=""),"",WORKDAY($B46,$K46)) | M46: =IF(OR($B46="",$I46=""),"",IF($G46="Completed","",$I46-AsOf)) | N46: =IF(OR($B46="",$J46=""),"",$J46-$B46) | O46: =IF($B46="","",IF($G46="Completed","",AsOf-$B46)) | P46: =IF($B46="","",IF($G46="Completed",IF(AND($J46<>"",$J46>$I46),"Done (Late)","Done"),IF($I46="","No deadline",IF($I46<AsOf,"OVERDUE",IF($I46-AsOf<=Lists!$B$9,"Due Soon","On Track"))))) | Q46: =IF(OR($B46="",$L46=""),"",IF($G46="Completed",IF($J46="","",IF($J46<=$L46,"Met","Missed")),IF(AsOf>$L46,"Breached","Within SLA"))) | R46: =IF($B46="","",IF($G46="Completed",0,IFERROR(INDEX(Lists!$C$5:$C$7,MATCH($F46,Lists!$A$5:$A$7,0)),1)*IF($I46="",1,IF($I46<AsOf,3,IF($I46-AsOf<=Lists!$B$9,2,1))))) | S46: =IF($B46="","",$R46+(1000-ROW())/100000) | T46: =IF($B46="","",IF(AND($G46="Completed",$J46=""),"Missing completion date",IF(AND($G46<>"Completed",$J46<>""),"Completion date on open request",IF(AND($I46<>"",$I46<$B46),"Deadline before raised","OK"))))
A47: DB-042 | K47: =IF($B47="","",IFERROR(INDEX(Lists!$B$5:$B$7,MATCH($F47,Lists!$A$5:$A$7,0)),"")) | L47: =IF(OR($B47="",$K47=""),"",WORKDAY($B47,$K47)) | M47: =IF(OR($B47="",$I47=""),"",IF($G47="Completed","",$I47-AsOf)) | N47: =IF(OR($B47="",$J47=""),"",$J47-$B47) | O47: =IF($B47="","",IF($G47="Completed","",AsOf-$B47)) | P47: =IF($B47="","",IF($G47="Completed",IF(AND($J47<>"",$J47>$I47),"Done (Late)","Done"),IF($I47="","No deadline",IF($I47<AsOf,"OVERDUE",IF($I47-AsOf<=Lists!$B$9,"Due Soon","On Track"))))) | Q47: =IF(OR($B47="",$L47=""),"",IF($G47="Completed",IF($J47="","",IF($J47<=$L47,"Met","Missed")),IF(AsOf>$L47,"Breached","Within SLA"))) | R47: =IF($B47="","",IF($G47="Completed",0,IFERROR(INDEX(Lists!$C$5:$C$7,MATCH($F47,Lists!$A$5:$A$7,0)),1)*IF($I47="",1,IF($I47<AsOf,3,IF($I47-AsOf<=Lists!$B$9,2,1))))) | S47: =IF($B47="","",$R47+(1000-ROW())/100000) | T47: =IF($B47="","",IF(AND($G47="Completed",$J47=""),"Missing completion date",IF(AND($G47<>"Completed",$J47<>""),"Completion date on open request",IF(AND($I47<>"",$I47<$B47),"Deadline before raised","OK"))))
A48: DB-043 | K48: =IF($B48="","",IFERROR(INDEX(Lists!$B$5:$B$7,MATCH($F48,Lists!$A$5:$A$7,0)),"")) | L48: =IF(OR($B48="",$K48=""),"",WORKDAY($B48,$K48)) | M48: =IF(OR($B48="",$I48=""),"",IF($G48="Completed","",$I48-AsOf)) | N48: =IF(OR($B48="",$J48=""),"",$J48-$B48) | O48: =IF($B48="","",IF($G48="Completed","",AsOf-$B48)) | P48: =IF($B48="","",IF($G48="Completed",IF(AND($J48<>"",$J48>$I48),"Done (Late)","Done"),IF($I48="","No deadline",IF($I48<AsOf,"OVERDUE",IF($I48-AsOf<=Lists!$B$9,"Due Soon","On Track"))))) | Q48: =IF(OR($B48="",$L48=""),"",IF($G48="Completed",IF($J48="","",IF($J48<=$L48,"Met","Missed")),IF(AsOf>$L48,"Breached","Within SLA"))) | R48: =IF($B48="","",IF($G48="Completed",0,IFERROR(INDEX(Lists!$C$5:$C$7,MATCH($F48,Lists!$A$5:$A$7,0)),1)*IF($I48="",1,IF($I48<AsOf,3,IF($I48-AsOf<=Lists!$B$9,2,1))))) | S48: =IF($B48="","",$R48+(1000-ROW())/100000) | T48: =IF($B48="","",IF(AND($G48="Completed",$J48=""),"Missing completion date",IF(AND($G48<>"Completed",$J48<>""),"Completion date on open request",IF(AND($I48<>"",$I48<$B48),"Deadline before raised","OK"))))
A49: DB-044 | K49: =IF($B49="","",IFERROR(INDEX(Lists!$B$5:$B$7,MATCH($F49,Lists!$A$5:$A$7,0)),"")) | L49: =IF(OR($B49="",$K49=""),"",WORKDAY($B49,$K49)) | M49: =IF(OR($B49="",$I49=""),"",IF($G49="Completed","",$I49-AsOf)) | N49: =IF(OR($B49="",$J49=""),"",$J49-$B49) | O49: =IF($B49="","",IF($G49="Completed","",AsOf-$B49)) | P49: =IF($B49="","",IF($G49="Completed",IF(AND($J49<>"",$J49>$I49),"Done (Late)","Done"),IF($I49="","No deadline",IF($I49<AsOf,"OVERDUE",IF($I49-AsOf<=Lists!$B$9,"Due Soon","On Track"))))) | Q49: =IF(OR($B49="",$L49=""),"",IF($G49="Completed",IF($J49="","",IF($J49<=$L49,"Met","Missed")),IF(AsOf>$L49,"Breached","Within SLA"))) | R49: =IF($B49="","",IF($G49="Completed",0,IFERROR(INDEX(Lists!$C$5:$C$7,MATCH($F49,Lists!$A$5:$A$7,0)),1)*IF($I49="",1,IF($I49<AsOf,3,IF($I49-AsOf<=Lists!$B$9,2,1))))) | S49: =IF($B49="","",$R49+(1000-ROW())/100000) | T49: =IF($B49="","",IF(AND($G49="Completed",$J49=""),"Missing completion date",IF(AND($G49<>"Completed",$J49<>""),"Completion date on open request",IF(AND($I49<>"",$I49<$B49),"Deadline before raised","OK"))))
A50: DB-045 | K50: =IF($B50="","",IFERROR(INDEX(Lists!$B$5:$B$7,MATCH($F50,Lists!$A$5:$A$7,0)),"")) | L50: =IF(OR($B50="",$K50=""),"",WORKDAY($B50,$K50)) | M50: =IF(OR($B50="",$I50=""),"",IF($G50="Completed","",$I50-AsOf)) | N50: =IF(OR($B50="",$J50=""),"",$J50-$B50) | O50: =IF($B50="","",IF($G50="Completed","",AsOf-$B50)) | P50: =IF($B50="","",IF($G50="Completed",IF(AND($J50<>"",$J50>$I50),"Done (Late)","Done"),IF($I50="","No deadline",IF($I50<AsOf,"OVERDUE",IF($I50-AsOf<=Lists!$B$9,"Due Soon","On Track"))))) | Q50: =IF(OR($B50="",$L50=""),"",IF($G50="Completed",IF($J50="","",IF($J50<=$L50,"Met","Missed")),IF(AsOf>$L50,"Breached","Within SLA"))) | R50: =IF($B50="","",IF($G50="Completed",0,IFERROR(INDEX(Lists!$C$5:$C$7,MATCH($F50,Lists!$A$5:$A$7,0)),1)*IF($I50="",1,IF($I50<AsOf,3,IF($I50-AsOf<=Lists!$B$9,2,1))))) | S50: =IF($B50="","",$R50+(1000-ROW())/100000) | T50: =IF($B50="","",IF(AND($G50="Completed",$J50=""),"Missing completion date",IF(AND($G50<>"Completed",$J50<>""),"Completion date on open request",IF(AND($I50<>"",$I50<$B50),"Deadline before raised","OK"))))
A51: DB-046 | K51: =IF($B51="","",IFERROR(INDEX(Lists!$B$5:$B$7,MATCH($F51,Lists!$A$5:$A$7,0)),"")) | L51: =IF(OR($B51="",$K51=""),"",WORKDAY($B51,$K51)) | M51: =IF(OR($B51="",$I51=""),"",IF($G51="Completed","",$I51-AsOf)) | N51: =IF(OR($B51="",$J51=""),"",$J51-$B51) | O51: =IF($B51="","",IF($G51="Completed","",AsOf-$B51)) | P51: =IF($B51="","",IF($G51="Completed",IF(AND($J51<>"",$J51>$I51),"Done (Late)","Done"),IF($I51="","No deadline",IF($I51<AsOf,"OVERDUE",IF($I51-AsOf<=Lists!$B$9,"Due Soon","On Track"))))) | Q51: =IF(OR($B51="",$L51=""),"",IF($G51="Completed",IF($J51="","",IF($J51<=$L51,"Met","Missed")),IF(AsOf>$L51,"Breached","Within SLA"))) | R51: =IF($B51="","",IF($G51="Completed",0,IFERROR(INDEX(Lists!$C$5:$C$7,MATCH($F51,Lists!$A$5:$A$7,0)),1)*IF($I51="",1,IF($I51<AsOf,3,IF($I51-AsOf<=Lists!$B$9,2,1))))) | S51: =IF($B51="","",$R51+(1000-ROW())/100000) | T51: =IF($B51="","",IF(AND($G51="Completed",$J51=""),"Missing completion date",IF(AND($G51<>"Completed",$J51<>""),"Completion date on open request",IF(AND($I51<>"",$I51<$B51),"Deadline before raised","OK"))))
A52: DB-047 | K52: =IF($B52="","",IFERROR(INDEX(Lists!$B$5:$B$7,MATCH($F52,Lists!$A$5:$A$7,0)),"")) | L52: =IF(OR($B52="",$K52=""),"",WORKDAY($B52,$K52)) | M52: =IF(OR($B52="",$I52=""),"",IF($G52="Completed","",$I52-AsOf)) | N52: =IF(OR($B52="",$J52=""),"",$J52-$B52) | O52: =IF($B52="","",IF($G52="Completed","",AsOf-$B52)) | P52: =IF($B52="","",IF($G52="Completed",IF(AND($J52<>"",$J52>$I52),"Done (Late)","Done"),IF($I52="","No deadline",IF($I52<AsOf,"OVERDUE",IF($I52-AsOf<=Lists!$B$9,"Due Soon","On Track"))))) | Q52: =IF(OR($B52="",$L52=""),"",IF($G52="Completed",IF($J52="","",IF($J52<=$L52,"Met","Missed")),IF(AsOf>$L52,"Breached","Within SLA"))) | R52: =IF($B52="","",IF($G52="Completed",0,IFERROR(INDEX(Lists!$C$5:$C$7,MATCH($F52,Lists!$A$5:$A$7,0)),1)*IF($I52="",1,IF($I52<AsOf,3,IF($I52-AsOf<=Lists!$B$9,2,1))))) | S52: =IF($B52="","",$R52+(1000-ROW())/100000) | T52: =IF($B52="","",IF(AND($G52="Completed",$J52=""),"Missing completion date",IF(AND($G52<>"Completed",$J52<>""),"Completion date on open request",IF(AND($I52<>"",$I52<$B52),"Deadline before raised","OK"))))
A53: DB-048 | K53: =IF($B53="","",IFERROR(INDEX(Lists!$B$5:$B$7,MATCH($F53,Lists!$A$5:$A$7,0)),"")) | L53: =IF(OR($B53="",$K53=""),"",WORKDAY($B53,$K53)) | M53: =IF(OR($B53="",$I53=""),"",IF($G53="Completed","",$I53-AsOf)) | N53: =IF(OR($B53="",$J53=""),"",$J53-$B53) | O53: =IF($B53="","",IF($G53="Completed","",AsOf-$B53)) | P53: =IF($B53="","",IF($G53="Completed",IF(AND($J53<>"",$J53>$I53),"Done (Late)","Done"),IF($I53="","No deadline",IF($I53<AsOf,"OVERDUE",IF($I53-AsOf<=Lists!$B$9,"Due Soon","On Track"))))) | Q53: =IF(OR($B53="",$L53=""),"",IF($G53="Completed",IF($J53="","",IF($J53<=$L53,"Met","Missed")),IF(AsOf>$L53,"Breached","Within SLA"))) | R53: =IF($B53="","",IF($G53="Completed",0,IFERROR(INDEX(Lists!$C$5:$C$7,MATCH($F53,Lists!$A$5:$A$7,0)),1)*IF($I53="",1,IF($I53<AsOf,3,IF($I53-AsOf<=Lists!$B$9,2,1))))) | S53: =IF($B53="","",$R53+(1000-ROW())/100000) | T53: =IF($B53="","",IF(AND($G53="Completed",$J53=""),"Missing completion date",IF(AND($G53<>"Completed",$J53<>""),"Completion date on open request",IF(AND($I53<>"",$I53<$B53),"Deadline before raised","OK"))))
A54: DB-049 | K54: =IF($B54="","",IFERROR(INDEX(Lists!$B$5:$B$7,MATCH($F54,Lists!$A$5:$A$7,0)),"")) | L54: =IF(OR($B54="",$K54=""),"",WORKDAY($B54,$K54)) | M54: =IF(OR($B54="",$I54=""),"",IF($G54="Completed","",$I54-AsOf)) | N54: =IF(OR($B54="",$J54=""),"",$J54-$B54) | O54: =IF($B54="","",IF($G54="Completed","",AsOf-$B54)) | P54: =IF($B54="","",IF($G54="Completed",IF(AND($J54<>"",$J54>$I54),"Done (Late)","Done"),IF($I54="","No deadline",IF($I54<AsOf,"OVERDUE",IF($I54-AsOf<=Lists!$B$9,"Due Soon","On Track"))))) | Q54: =IF(OR($B54="",$L54=""),"",IF($G54="Completed",IF($J54="","",IF($J54<=$L54,"Met","Missed")),IF(AsOf>$L54,"Breached","Within SLA"))) | R54: =IF($B54="","",IF($G54="Completed",0,IFERROR(INDEX(Lists!$C$5:$C$7,MATCH($F54,Lists!$A$5:$A$7,0)),1)*IF($I54="",1,IF($I54<AsOf,3,IF($I54-AsOf<=Lists!$B$9,2,1))))) | S54: =IF($B54="","",$R54+(1000-ROW())/100000) | T54: =IF($B54="","",IF(AND($G54="Completed",$J54=""),"Missing completion date",IF(AND($G54<>"Completed",$J54<>""),"Completion date on open request",IF(AND($I54<>"",$I54<$B54),"Deadline before raised","OK"))))
A55: DB-050 | K55: =IF($B55="","",IFERROR(INDEX(Lists!$B$5:$B$7,MATCH($F55,Lists!$A$5:$A$7,0)),"")) | L55: =IF(OR($B55="",$K55=""),"",WORKDAY($B55,$K55)) | M55: =IF(OR($B55="",$I55=""),"",IF($G55="Completed","",$I55-AsOf)) | N55: =IF(OR($B55="",$J55=""),"",$J55-$B55) | O55: =IF($B55="","",IF($G55="Completed","",AsOf-$B55)) | P55: =IF($B55="","",IF($G55="Completed",IF(AND($J55<>"",$J55>$I55),"Done (Late)","Done"),IF($I55="","No deadline",IF($I55<AsOf,"OVERDUE",IF($I55-AsOf<=Lists!$B$9,"Due Soon","On Track"))))) | Q55: =IF(OR($B55="",$L55=""),"",IF($G55="Completed",IF($J55="","",IF($J55<=$L55,"Met","Missed")),IF(AsOf>$L55,"Breached","Within SLA"))) | R55: =IF($B55="","",IF($G55="Completed",0,IFERROR(INDEX(Lists!$C$5:$C$7,MATCH($F55,Lists!$A$5:$A$7,0)),1)*IF($I55="",1,IF($I55<AsOf,3,IF($I55-AsOf<=Lists!$B$9,2,1))))) | S55: =IF($B55="","",$R55+(1000-ROW())/100000) | T55: =IF($B55="","",IF(AND($G55="Completed",$J55=""),"Missing completion date",IF(AND($G55<>"Completed",$J55<>""),"Completion date on open request",IF(AND($I55<>"",$I55<$B55),"Deadline before raised","OK"))))
A56: DB-051 | K56: =IF($B56="","",IFERROR(INDEX(Lists!$B$5:$B$7,MATCH($F56,Lists!$A$5:$A$7,0)),"")) | L56: =IF(OR($B56="",$K56=""),"",WORKDAY($B56,$K56)) | M56: =IF(OR($B56="",$I56=""),"",IF($G56="Completed","",$I56-AsOf)) | N56: =IF(OR($B56="",$J56=""),"",$J56-$B56) | O56: =IF($B56="","",IF($G56="Completed","",AsOf-$B56)) | P56: =IF($B56="","",IF($G56="Completed",IF(AND($J56<>"",$J56>$I56),"Done (Late)","Done"),IF($I56="","No deadline",IF($I56<AsOf,"OVERDUE",IF($I56-AsOf<=Lists!$B$9,"Due Soon","On Track"))))) | Q56: =IF(OR($B56="",$L56=""),"",IF($G56="Completed",IF($J56="","",IF($J56<=$L56,"Met","Missed")),IF(AsOf>$L56,"Breached","Within SLA"))) | R56: =IF($B56="","",IF($G56="Completed",0,IFERROR(INDEX(Lists!$C$5:$C$7,MATCH($F56,Lists!$A$5:$A$7,0)),1)*IF($I56="",1,IF($I56<AsOf,3,IF($I56-AsOf<=Lists!$B$9,2,1))))) | S56: =IF($B56="","",$R56+(1000-ROW())/100000) | T56: =IF($B56="","",IF(AND($G56="Completed",$J56=""),"Missing completion date",IF(AND($G56<>"Completed",$J56<>""),"Completion date on open request",IF(AND($I56<>"",$I56<$B56),"Deadline before raised","OK"))))
A57: DB-052 | K57: =IF($B57="","",IFERROR(INDEX(Lists!$B$5:$B$7,MATCH($F57,Lists!$A$5:$A$7,0)),"")) | L57: =IF(OR($B57="",$K57=""),"",WORKDAY($B57,$K57)) | M57: =IF(OR($B57="",$I57=""),"",IF($G57="Completed","",$I57-AsOf)) | N57: =IF(OR($B57="",$J57=""),"",$J57-$B57) | O57: =IF($B57="","",IF($G57="Completed","",AsOf-$B57)) | P57: =IF($B57="","",IF($G57="Completed",IF(AND($J57<>"",$J57>$I57),"Done (Late)","Done"),IF($I57="","No deadline",IF($I57<AsOf,"OVERDUE",IF($I57-AsOf<=Lists!$B$9,"Due Soon","On Track"))))) | Q57: =IF(OR($B57="",$L57=""),"",IF($G57="Completed",IF($J57="","",IF($J57<=$L57,"Met","Missed")),IF(AsOf>$L57,"Breached","Within SLA"))) | R57: =IF($B57="","",IF($G57="Completed",0,IFERROR(INDEX(Lists!$C$5:$C$7,MATCH($F57,Lists!$A$5:$A$7,0)),1)*IF($I57="",1,IF($I57<AsOf,3,IF($I57-AsOf<=Lists!$B$9,2,1))))) | S57: =IF($B57="","",$R57+(1000-ROW())/100000) | T57: =IF($B57="","",IF(AND($G57="Completed",$J57=""),"Missing completion date",IF(AND($G57<>"Completed",$J57<>""),"Completion date on open request",IF(AND($I57<>"",$I57<$B57),"Deadline before raised","OK"))))
... A65: DB-060 | K65: =IF($B65="","",IFERROR(INDEX(Lists!$B$5:$B$7,MATCH($F65,Lists!$A$5:$A$7,0)),"")) | L65: =IF(OR($B65="",$K65=""),"",WORKDAY($B65,$K65)) | M65: =IF(OR($B65="",$I65=""),"",IF($G65="Completed","",$I65-AsOf)) | N65: =IF(OR($B65="",$J65=""),"",$J65-$B65) | O65: =IF($B65="","",IF($G65="Completed","",AsOf-$B65)) | P65: =IF($B65="","",IF($G65="Completed",IF(AND($J65<>"",$J65>$I65),"Done (Late)","Done"),IF($I65="","No deadline",IF($I65<AsOf,"OVERDUE",IF($I65-AsOf<=Lists!$B$9,"Due Soon","On Track"))))) | Q65: =IF(OR($B65="",$L65=""),"",IF($G65="Completed",IF($J65="","",IF($J65<=$L65,"Met","Missed")),IF(AsOf>$L65,"Breached","Within SLA"))) | R65: =IF($B65="","",IF($G65="Completed",0,IFERROR(INDEX(Lists!$C$5:$C$7,MATCH($F65,Lists!$A$5:$A$7,0)),1)*IF($I65="",1,IF($I65<AsOf,3,IF($I65-AsOf<=Lists!$B$9,2,1))))) | S65: =IF($B65="","",$R65+(1000-ROW())/100000) | T65: =IF($B65="","",IF(AND($G65="Completed",$J65=""),"Missing completion date",IF(AND($G65<>"Completed",$J65<>""),"Completion date on open request",IF(AND($I65<>"",$I65<$B65),"Deadline before raised","OK"))))

Sheet Team
A1: Team Roster and Capacity (fictional)
A2: Capacity = maximum open requests a person can reasonably handle at once.
A4: Name | B4: Department | C4: Capacity
A5: Ayesha Khan | B5: Digital Banking | C5: 8
A6: Hamza Malik | B6: IT | C6: 8
A7: Sana Raza | B7: Operations | C7: 7
A8: Bilal Ahmed | B8: Compliance | C8: 6
A9: Fatima Noor | B9: Customer Support | C9: 7
A10: Usman Tariq | B10: Risk | C10: 5
A11: Zainab Ali | B11: Finance | C11: 6
A12: Omar Siddiqui | B12: Digital Banking | C12: 8

Sheet Lists
A1: Reference Lists and Assumptions
A2: Assumption: SLA working days and priority weights are fictional values chosen for this portfolio project.
A4: Priority | B4: SLA (working days) | C4: Weight | E4: Status | G4: Department | I4: Request Type
A5: High | B5: 2 | C5: 3 | E5: Pending | G5: IT | I5: Access Request
A6: Medium | B6: 5 | C6: 2 | E6: In Progress | G6: Operations | I6: Report
A7: Low | B7: 8 | C7: 1 | E7: Completed | G7: Digital Banking | I7: Testing Support
G8: Compliance | I8: Incident Fix
A9: Due Soon window (days) | B9: 2 | G9: Customer Support | I9: Compliance Review
A10: Flag logic: OVERDUE if deadline < as-of date; Due Soon if within the window above. | G10: Risk | I10: Documentation
G11: Marketing | I11: Change Request
G12: Finance

Sheet How To Use
A1: How to use this tracker
A2: Sheets: Dashboard (summary and charts), Request Tracker (data entry), Team (roster and capacity), Lists (dropdown values and assumptions).
A3: 1. Add a new request in the next empty row of 'Request Tracker'. Fill only the yellow columns A to J; the rest calculates.
A4: 2. Use the dropdowns for Department, Request Type, Priority, Status and Assigned To. Deadline cannot be earlier than Date Raised.
A5: 3. SLA target = Date Raised plus the priority's SLA working days (Mon to Fri), set on the Lists sheet.
A6: 4. Flag: Done / Done (Late) / OVERDUE / Due Soon / On Track. SLA Status: Met / Missed for completed, Within SLA / Breached for open.
A7: 5. Risk Score = priority weight (3/2/1) x urgency (3 overdue, 2 due soon, 1 otherwise). Completed requests score 0.
A8: 6. Data Check flags rows with inconsistent dates or status; results roll up to the Dashboard (section 6).
A9: 7. To test the logic, type a date into the yellow cell C4 on the Dashboard. Clear it to return to today's date.
A10: 8. Use the filter arrows on the Request Tracker header row to sort or filter, e.g. Flag = OVERDUE or Assigned To = one person.
A11: Colour guide on tracker rows: red = overdue, amber = due soon, green = completed.
A12: All data is fictional and created for portfolio purposes.
